{
  "accelerator_path": "/tmp/prometheus-r176-overlay-0469ab075ef40a84/qiskit/_accelerate.abi3.so",
  "accelerator_sha256": "0469ab075ef40a841da017e2b9cebeac5fe2c1ac8fc95b77c99dc773ea3ff054",
  "contract_payload_hash": "1612b5140aecb82024f8db34a12df87fcdcc9e4989f013a82eac3b4cae6cd96e",
  "dataset_id": "r169_non_tie",
  "elapsed_ns_median": 26068.5,
  "elapsed_ns_p95_nearest_rank": 30377,
  "environment": {
    "github_run_attempt": "1",
    "github_run_id": "29757057658",
    "machine": "x86_64",
    "platform": "Linux-6.17.0-1020-azure-x86_64-with-glibc2.39",
    "python": "3.12.13",
    "pythonpath_head": "/home/runner/work/Prometheus-plan/Prometheus-plan/tools",
    "qiskit": "2.4.1",
    "qiskit_aer": "0.17.2",
    "qiskit_ibm_runtime": "0.46.1",
    "system": "Linux"
  },
  "identity": "r169_non_tie__ascending_sorted_order",
  "input_qasm_sha256": "d6895b30e27cc9f75e93edffef348d1701526c077ba1121094c394b38fb68fb7",
  "kind": "standard",
  "manifest_hash": "93e2c32c041e8fbf5f582b9b6f702bec81517c495aec0f03a8e0e3b4e804efa7",
  "peak_rss": 214144,
  "peak_rss_unit": "kibibytes",
  "policy": "rust_biguint_exact_retained_binary64",
  "preregistration": {
    "commit": "f4e99da05d9e1211fcb3a239144d6355f5cd8055",
    "created_at": "2026-07-20T15:50:41Z",
    "discussion": "https://github.com/crystal-tensor/Prometheus-plan/discussions/268"
  },
  "process_id": 10812,
  "process_instance_uuid": "ad470b64-c25e-4392-98fb-e51542dbc19a",
  "profile_id": "ascending_sorted_order",
  "protocol_payload_hash": "4c4899bb0e65de1387585ae034b884bb5508b5d01bf7775d670b65a7360b536d",
  "recorded_call_count": 64,
  "recorded_matches_expected": 64,
  "replay_rows": [
    {
      "dataset_id": "r169_non_tie",
      "elapsed_ns": 25808,
      "exact_expected_mapping_vector": [
        0,
        6,
        5,
        4,
        3,
        1,
        2
      ],
      "expected_mapping_vector": [
        0,
        6,
        5,
        4,
        3,
        1,
        2
      ],
      "kind": "standard",
      "mapping_vector": [
        0,
        6,
        5,
        4,
        3,
        1,
        2
      ],
      "matches_expected": true,
      "policy": "rust_biguint_exact_retained_binary64",
      "profile_id": "ascending_sorted_order",
      "replay_index": 0,
      "row_hash": "9eb827288aa8189399ac3109134d46cf68776d73219e01a18404e78b209a4e77",
      "simulation_execution_count": 0,
      "source_expected_mapping_vector": [
        0,
        6,
        5,
        4,
        3,
        1,
        2
      ],
      "total_simulated_shots": 0
    },
    {
      "dataset_id": "r169_non_tie",
      "elapsed_ns": 31348,
      "exact_expected_mapping_vector": [
        0,
        6,
        5,
        4,
        3,
        1,
        2
      ],
      "expected_mapping_vector": [
        0,
        6,
        5,
        4,
        3,
        1,
        2
      ],
      "kind": "standard",
      "mapping_vector": [
        0,
        6,
        5,
        4,
        3,
        1,
        2
      ],
      "matches_expected": true,
      "policy": "rust_biguint_exact_retained_binary64",
      "profile_id": "ascending_sorted_order",
      "replay_index": 1,
      "row_hash": "3530e3756f56b0b5a02f9ebae2746fdcdec8d21f1680207f95293167190a3902",
      "simulation_execution_count": 0,
      "source_expected_mapping_vector": [
        0,
        6,
        5,
        4,
        3,
        1,
        2
      ],
      "total_simulated_shots": 0
    },
    {
      "dataset_id": "r169_non_tie",
      "elapsed_ns": 28523,
      "exact_expected_mapping_vector": [
        0,
        6,
        5,
        4,
        3,
        1,
        2
      ],
      "expected_mapping_vector": [
        0,
        6,
        5,
        4,
        3,
        1,
        2
      ],
      "kind": "standard",
      "mapping_vector": [
        0,
        6,
        5,
        4,
        3,
        1,
        2
      ],
      "matches_expected": true,
      "policy": "rust_biguint_exact_retained_binary64",
      "profile_id": "ascending_sorted_order",
      "replay_index": 2,
      "row_hash": "60751d4145042c7ca7e454ff496d0973422ae1c16d7c98e09a468934df2290a8",
      "simulation_execution_count": 0,
      "source_expected_mapping_vector": [
        0,
        6,
        5,
        4,
        3,
        1,
        2
      ],
      "total_simulated_shots": 0
    },
    {
      "dataset_id": "r169_non_tie",
      "elapsed_ns": 27592,
      "exact_expected_mapping_vector": [
        0,
        6,
        5,
        4,
        3,
        1,
        2
      ],
      "expected_mapping_vector": [
        0,
        6,
        5,
        4,
        3,
        1,
        2
      ],
      "kind": "standard",
      "mapping_vector": [
        0,
        6,
        5,
        4,
        3,
        1,
        2
      ],
      "matches_expected": true,
      "policy": "rust_biguint_exact_retained_binary64",
      "profile_id": "ascending_sorted_order",
      "replay_index": 3,
      "row_hash": "c4da0e3b06ed0ec1aed36965bda1ae4d33555cf20f5ca0223741b8a7af27b16c",
      "simulation_execution_count": 0,
      "source_expected_mapping_vector": [
        0,
        6,
        5,
        4,
        3,
        1,
        2
      ],
      "total_simulated_shots": 0
    },
    {
      "dataset_id": "r169_non_tie",
      "elapsed_ns": 49001,
      "exact_expected_mapping_vector": [
        0,
        6,
        5,
        4,
        3,
        1,
        2
      ],
      "expected_mapping_vector": [
        0,
        6,
        5,
        4,
        3,
        1,
        2
      ],
      "kind": "standard",
      "mapping_vector": [
        0,
        6,
        5,
        4,
        3,
        1,
        2
      ],
      "matches_expected": true,
      "policy": "rust_biguint_exact_retained_binary64",
      "profile_id": "ascending_sorted_order",
      "replay_index": 4,
      "row_hash": "02cd9a763920b2f26963f4b3b72ede2a05074583993ac2600399f465da5b62f8",
      "simulation_execution_count": 0,
      "source_expected_mapping_vector": [
        0,
        6,
        5,
        4,
        3,
        1,
        2
      ],
      "total_simulated_shots": 0
    },
    {
      "dataset_id": "r169_non_tie",
      "elapsed_ns": 31118,
      "exact_expected_mapping_vector": [
        0,
        6,
        5,
        4,
        3,
        1,
        2
      ],
      "expected_mapping_vector": [
        0,
        6,
        5,
        4,
        3,
        1,
        2
      ],
      "kind": "standard",
      "mapping_vector": [
        0,
        6,
        5,
        4,
        3,
        1,
        2
      ],
      "matches_expected": true,
      "policy": "rust_biguint_exact_retained_binary64",
      "profile_id": "ascending_sorted_order",
      "replay_index": 5,
      "row_hash": "5aa45ab63da65c3b4e3f1ef63d679e68bc6a128695270acd6965e980f8d99f46",
      "simulation_execution_count": 0,
      "source_expected_mapping_vector": [
        0,
        6,
        5,
        4,
        3,
        1,
        2
      ],
      "total_simulated_shots": 0
    },
    {
      "dataset_id": "r169_non_tie",
      "elapsed_ns": 27211,
      "exact_expected_mapping_vector": [
        0,
        6,
        5,
        4,
        3,
        1,
        2
      ],
      "expected_mapping_vector": [
        0,
        6,
        5,
        4,
        3,
        1,
        2
      ],
      "kind": "standard",
      "mapping_vector": [
        0,
        6,
        5,
        4,
        3,
        1,
        2
      ],
      "matches_expected": true,
      "policy": "rust_biguint_exact_retained_binary64",
      "profile_id": "ascending_sorted_order",
      "replay_index": 6,
      "row_hash": "4015b417c766e02e55fd228bddbfeb0c5aee9daba8e17fdbf54160b651a31831",
      "simulation_execution_count": 0,
      "source_expected_mapping_vector": [
        0,
        6,
        5,
        4,
        3,
        1,
        2
      ],
      "total_simulated_shots": 0
    },
    {
      "dataset_id": "r169_non_tie",
      "elapsed_ns": 27762,
      "exact_expected_mapping_vector": [
        0,
        6,
        5,
        4,
        3,
        1,
        2
      ],
      "expected_mapping_vector": [
        0,
        6,
        5,
        4,
        3,
        1,
        2
      ],
      "kind": "standard",
      "mapping_vector": [
        0,
        6,
        5,
        4,
        3,
        1,
        2
      ],
      "matches_expected": true,
      "policy": "rust_biguint_exact_retained_binary64",
      "profile_id": "ascending_sorted_order",
      "replay_index": 7,
      "row_hash": "9763d1b3663dfdb5e09cc0702f6270d5b8b187543320865497ccb5976c32b066",
      "simulation_execution_count": 0,
      "source_expected_mapping_vector": [
        0,
        6,
        5,
        4,
        3,
        1,
        2
      ],
      "total_simulated_shots": 0
    },
    {
      "dataset_id": "r169_non_tie",
      "elapsed_ns": 26710,
      "exact_expected_mapping_vector": [
        0,
        6,
        5,
        4,
        3,
        1,
        2
      ],
      "expected_mapping_vector": [
        0,
        6,
        5,
        4,
        3,
        1,
        2
      ],
      "kind": "standard",
      "mapping_vector": [
        0,
        6,
        5,
        4,
        3,
        1,
        2
      ],
      "matches_expected": true,
      "policy": "rust_biguint_exact_retained_binary64",
      "profile_id": "ascending_sorted_order",
      "replay_index": 8,
      "row_hash": "339e0e6dc4e530a27e0eed92d1240d3a04c85fca7603f978b5502d6467be9b8c",
      "simulation_execution_count": 0,
      "source_expected_mapping_vector": [
        0,
        6,
        5,
        4,
        3,
        1,
        2
      ],
      "total_simulated_shots": 0
    },
    {
      "dataset_id": "r169_non_tie",
      "elapsed_ns": 26138,
      "exact_expected_mapping_vector": [
        0,
        6,
        5,
        4,
        3,
        1,
        2
      ],
      "expected_mapping_vector": [
        0,
        6,
        5,
        4,
        3,
        1,
        2
      ],
      "kind": "standard",
      "mapping_vector": [
        0,
        6,
        5,
        4,
        3,
        1,
        2
      ],
      "matches_expected": true,
      "policy": "rust_biguint_exact_retained_binary64",
      "profile_id": "ascending_sorted_order",
      "replay_index": 9,
      "row_hash": "1193ec7167839c60d03bcbefb42e561fec01013f0ffa133256d0900c3a2f18a2",
      "simulation_execution_count": 0,
      "source_expected_mapping_vector": [
        0,
        6,
        5,
        4,
        3,
        1,
        2
      ],
      "total_simulated_shots": 0
    },
    {
      "dataset_id": "r169_non_tie",
      "elapsed_ns": 26469,
      "exact_expected_mapping_vector": [
        0,
        6,
        5,
        4,
        3,
        1,
        2
      ],
      "expected_mapping_vector": [
        0,
        6,
        5,
        4,
        3,
        1,
        2
      ],
      "kind": "standard",
      "mapping_vector": [
        0,
        6,
        5,
        4,
        3,
        1,
        2
      ],
      "matches_expected": true,
      "policy": "rust_biguint_exact_retained_binary64",
      "profile_id": "ascending_sorted_order",
      "replay_index": 10,
      "row_hash": "33ceecfded7819de40c51c3917cee8d9584c4a80288e07315685241a0fb3ca76",
      "simulation_execution_count": 0,
      "source_expected_mapping_vector": [
        0,
        6,
        5,
        4,
        3,
        1,
        2
      ],
      "total_simulated_shots": 0
    },
    {
      "dataset_id": "r169_non_tie",
      "elapsed_ns": 30377,
      "exact_expected_mapping_vector": [
        0,
        6,
        5,
        4,
        3,
        1,
        2
      ],
      "expected_mapping_vector": [
        0,
        6,
        5,
        4,
        3,
        1,
        2
      ],
      "kind": "standard",
      "mapping_vector": [
        0,
        6,
        5,
        4,
        3,
        1,
        2
      ],
      "matches_expected": true,
      "policy": "rust_biguint_exact_retained_binary64",
      "profile_id": "ascending_sorted_order",
      "replay_index": 11,
      "row_hash": "b3e2de86272b87d2ea1bd07bb0df4df4f7b650e2030c202ae9e842207d59efdd",
      "simulation_execution_count": 0,
      "source_expected_mapping_vector": [
        0,
        6,
        5,
        4,
        3,
        1,
        2
      ],
      "total_simulated_shots": 0
    },
    {
      "dataset_id": "r169_non_tie",
      "elapsed_ns": 27561,
      "exact_expected_mapping_vector": [
        0,
        6,
        5,
        4,
        3,
        1,
        2
      ],
      "expected_mapping_vector": [
        0,
        6,
        5,
        4,
        3,
        1,
        2
      ],
      "kind": "standard",
      "mapping_vector": [
        0,
        6,
        5,
        4,
        3,
        1,
        2
      ],
      "matches_expected": true,
      "policy": "rust_biguint_exact_retained_binary64",
      "profile_id": "ascending_sorted_order",
      "replay_index": 12,
      "row_hash": "092f2033116592aa087d8fe31cd11d0e3e1a45e733107edbf75fa375e3f0b543",
      "simulation_execution_count": 0,
      "source_expected_mapping_vector": [
        0,
        6,
        5,
        4,
        3,
        1,
        2
      ],
      "total_simulated_shots": 0
    },
    {
      "dataset_id": "r169_non_tie",
      "elapsed_ns": 27371,
      "exact_expected_mapping_vector": [
        0,
        6,
        5,
        4,
        3,
        1,
        2
      ],
      "expected_mapping_vector": [
        0,
        6,
        5,
        4,
        3,
        1,
        2
      ],
      "kind": "standard",
      "mapping_vector": [
        0,
        6,
        5,
        4,
        3,
        1,
        2
      ],
      "matches_expected": true,
      "policy": "rust_biguint_exact_retained_binary64",
      "profile_id": "ascending_sorted_order",
      "replay_index": 13,
      "row_hash": "d33b12124ce31c604b490a9362316f1490111fc989ffd2291ff6bb21fd6a3003",
      "simulation_execution_count": 0,
      "source_expected_mapping_vector": [
        0,
        6,
        5,
        4,
        3,
        1,
        2
      ],
      "total_simulated_shots": 0
    },
    {
      "dataset_id": "r169_non_tie",
      "elapsed_ns": 27000,
      "exact_expected_mapping_vector": [
        0,
        6,
        5,
        4,
        3,
        1,
        2
      ],
      "expected_mapping_vector": [
        0,
        6,
        5,
        4,
        3,
        1,
        2
      ],
      "kind": "standard",
      "mapping_vector": [
        0,
        6,
        5,
        4,
        3,
        1,
        2
      ],
      "matches_expected": true,
      "policy": "rust_biguint_exact_retained_binary64",
      "profile_id": "ascending_sorted_order",
      "replay_index": 14,
      "row_hash": "f7dd2ca25eeec4111d792fe6b16d7b3bf5c9526c02b2decc456d09449adb1ae6",
      "simulation_execution_count": 0,
      "source_expected_mapping_vector": [
        0,
        6,
        5,
        4,
        3,
        1,
        2
      ],
      "total_simulated_shots": 0
    },
    {
      "dataset_id": "r169_non_tie",
      "elapsed_ns": 26539,
      "exact_expected_mapping_vector": [
        0,
        6,
        5,
        4,
        3,
        1,
        2
      ],
      "expected_mapping_vector": [
        0,
        6,
        5,
        4,
        3,
        1,
        2
      ],
      "kind": "standard",
      "mapping_vector": [
        0,
        6,
        5,
        4,
        3,
        1,
        2
      ],
      "matches_expected": true,
      "policy": "rust_biguint_exact_retained_binary64",
      "profile_id": "ascending_sorted_order",
      "replay_index": 15,
      "row_hash": "0b531f9f7274e7797a07986f53411b287200076abb7f74844f4cf905a9466900",
      "simulation_execution_count": 0,
      "source_expected_mapping_vector": [
        0,
        6,
        5,
        4,
        3,
        1,
        2
      ],
      "total_simulated_shots": 0
    },
    {
      "dataset_id": "r169_non_tie",
      "elapsed_ns": 26239,
      "exact_expected_mapping_vector": [
        0,
        6,
        5,
        4,
        3,
        1,
        2
      ],
      "expected_mapping_vector": [
        0,
        6,
        5,
        4,
        3,
        1,
        2
      ],
      "kind": "standard",
      "mapping_vector": [
        0,
        6,
        5,
        4,
        3,
        1,
        2
      ],
      "matches_expected": true,
      "policy": "rust_biguint_exact_retained_binary64",
      "profile_id": "ascending_sorted_order",
      "replay_index": 16,
      "row_hash": "33273f2989be0c7891f39d3dd375f4c1950870969c0019da3c99339382509252",
      "simulation_execution_count": 0,
      "source_expected_mapping_vector": [
        0,
        6,
        5,
        4,
        3,
        1,
        2
      ],
      "total_simulated_shots": 0
    },
    {
      "dataset_id": "r169_non_tie",
      "elapsed_ns": 26149,
      "exact_expected_mapping_vector": [
        0,
        6,
        5,
        4,
        3,
        1,
        2
      ],
      "expected_mapping_vector": [
        0,
        6,
        5,
        4,
        3,
        1,
        2
      ],
      "kind": "standard",
      "mapping_vector": [
        0,
        6,
        5,
        4,
        3,
        1,
        2
      ],
      "matches_expected": true,
      "policy": "rust_biguint_exact_retained_binary64",
      "profile_id": "ascending_sorted_order",
      "replay_index": 17,
      "row_hash": "dd055cca1aa086ee8b41f7677753022816ee9d7392a3696fcb7ccc08688d47a9",
      "simulation_execution_count": 0,
      "source_expected_mapping_vector": [
        0,
        6,
        5,
        4,
        3,
        1,
        2
      ],
      "total_simulated_shots": 0
    },
    {
      "dataset_id": "r169_non_tie",
      "elapsed_ns": 26008,
      "exact_expected_mapping_vector": [
        0,
        6,
        5,
        4,
        3,
        1,
        2
      ],
      "expected_mapping_vector": [
        0,
        6,
        5,
        4,
        3,
        1,
        2
      ],
      "kind": "standard",
      "mapping_vector": [
        0,
        6,
        5,
        4,
        3,
        1,
        2
      ],
      "matches_expected": true,
      "policy": "rust_biguint_exact_retained_binary64",
      "profile_id": "ascending_sorted_order",
      "replay_index": 18,
      "row_hash": "08c670e2bc49f8764a7c9705dae6525ca2107c81e32bcbb01e37a2d7f8f90ed8",
      "simulation_execution_count": 0,
      "source_expected_mapping_vector": [
        0,
        6,
        5,
        4,
        3,
        1,
        2
      ],
      "total_simulated_shots": 0
    },
    {
      "dataset_id": "r169_non_tie",
      "elapsed_ns": 26149,
      "exact_expected_mapping_vector": [
        0,
        6,
        5,
        4,
        3,
        1,
        2
      ],
      "expected_mapping_vector": [
        0,
        6,
        5,
        4,
        3,
        1,
        2
      ],
      "kind": "standard",
      "mapping_vector": [
        0,
        6,
        5,
        4,
        3,
        1,
        2
      ],
      "matches_expected": true,
      "policy": "rust_biguint_exact_retained_binary64",
      "profile_id": "ascending_sorted_order",
      "replay_index": 19,
      "row_hash": "a73c3cecd21da1cfa82b631d4e402659bb3fb172aa446f6edf41c8e6b86fc5ae",
      "simulation_execution_count": 0,
      "source_expected_mapping_vector": [
        0,
        6,
        5,
        4,
        3,
        1,
        2
      ],
      "total_simulated_shots": 0
    },
    {
      "dataset_id": "r169_non_tie",
      "elapsed_ns": 26189,
      "exact_expected_mapping_vector": [
        0,
        6,
        5,
        4,
        3,
        1,
        2
      ],
      "expected_mapping_vector": [
        0,
        6,
        5,
        4,
        3,
        1,
        2
      ],
      "kind": "standard",
      "mapping_vector": [
        0,
        6,
        5,
        4,
        3,
        1,
        2
      ],
      "matches_expected": true,
      "policy": "rust_biguint_exact_retained_binary64",
      "profile_id": "ascending_sorted_order",
      "replay_index": 20,
      "row_hash": "e94082e268012a5dd3bf775de9ee35667f4b47b35f7eb7146715bcda64a87dc1",
      "simulation_execution_count": 0,
      "source_expected_mapping_vector": [
        0,
        6,
        5,
        4,
        3,
        1,
        2
      ],
      "total_simulated_shots": 0
    },
    {
      "dataset_id": "r169_non_tie",
      "elapsed_ns": 25918,
      "exact_expected_mapping_vector": [
        0,
        6,
        5,
        4,
        3,
        1,
        2
      ],
      "expected_mapping_vector": [
        0,
        6,
        5,
        4,
        3,
        1,
        2
      ],
      "kind": "standard",
      "mapping_vector": [
        0,
        6,
        5,
        4,
        3,
        1,
        2
      ],
      "matches_expected": true,
      "policy": "rust_biguint_exact_retained_binary64",
      "profile_id": "ascending_sorted_order",
      "replay_index": 21,
      "row_hash": "f6ea78969b90a1aefe76f312d2e54a8a46c736dfd07c2ca18a8af8ccef0af4fc",
      "simulation_execution_count": 0,
      "source_expected_mapping_vector": [
        0,
        6,
        5,
        4,
        3,
        1,
        2
      ],
      "total_simulated_shots": 0
    },
    {
      "dataset_id": "r169_non_tie",
      "elapsed_ns": 26109,
      "exact_expected_mapping_vector": [
        0,
        6,
        5,
        4,
        3,
        1,
        2
      ],
      "expected_mapping_vector": [
        0,
        6,
        5,
        4,
        3,
        1,
        2
      ],
      "kind": "standard",
      "mapping_vector": [
        0,
        6,
        5,
        4,
        3,
        1,
        2
      ],
      "matches_expected": true,
      "policy": "rust_biguint_exact_retained_binary64",
      "profile_id": "ascending_sorted_order",
      "replay_index": 22,
      "row_hash": "6656065adda47c6c97ab1347e41a5907a89d94320b7d26bf4e119da60c9b774b",
      "simulation_execution_count": 0,
      "source_expected_mapping_vector": [
        0,
        6,
        5,
        4,
        3,
        1,
        2
      ],
      "total_simulated_shots": 0
    },
    {
      "dataset_id": "r169_non_tie",
      "elapsed_ns": 25608,
      "exact_expected_mapping_vector": [
        0,
        6,
        5,
        4,
        3,
        1,
        2
      ],
      "expected_mapping_vector": [
        0,
        6,
        5,
        4,
        3,
        1,
        2
      ],
      "kind": "standard",
      "mapping_vector": [
        0,
        6,
        5,
        4,
        3,
        1,
        2
      ],
      "matches_expected": true,
      "policy": "rust_biguint_exact_retained_binary64",
      "profile_id": "ascending_sorted_order",
      "replay_index": 23,
      "row_hash": "8c7a334bdb721bde48fa329a7aadd53fb99457dca50d185e92c36c62eba55b68",
      "simulation_execution_count": 0,
      "source_expected_mapping_vector": [
        0,
        6,
        5,
        4,
        3,
        1,
        2
      ],
      "total_simulated_shots": 0
    },
    {
      "dataset_id": "r169_non_tie",
      "elapsed_ns": 25888,
      "exact_expected_mapping_vector": [
        0,
        6,
        5,
        4,
        3,
        1,
        2
      ],
      "expected_mapping_vector": [
        0,
        6,
        5,
        4,
        3,
        1,
        2
      ],
      "kind": "standard",
      "mapping_vector": [
        0,
        6,
        5,
        4,
        3,
        1,
        2
      ],
      "matches_expected": true,
      "policy": "rust_biguint_exact_retained_binary64",
      "profile_id": "ascending_sorted_order",
      "replay_index": 24,
      "row_hash": "6475bbe80cb5a049eafa517067f16d33b86cda4a73bb2c3805ab8d40f2f1c5d5",
      "simulation_execution_count": 0,
      "source_expected_mapping_vector": [
        0,
        6,
        5,
        4,
        3,
        1,
        2
      ],
      "total_simulated_shots": 0
    },
    {
      "dataset_id": "r169_non_tie",
      "elapsed_ns": 25978,
      "exact_expected_mapping_vector": [
        0,
        6,
        5,
        4,
        3,
        1,
        2
      ],
      "expected_mapping_vector": [
        0,
        6,
        5,
        4,
        3,
        1,
        2
      ],
      "kind": "standard",
      "mapping_vector": [
        0,
        6,
        5,
        4,
        3,
        1,
        2
      ],
      "matches_expected": true,
      "policy": "rust_biguint_exact_retained_binary64",
      "profile_id": "ascending_sorted_order",
      "replay_index": 25,
      "row_hash": "ce9196a3fa95f6239a3449866473c3198550e03f83aef50c7cc7c56a3b92cbed",
      "simulation_execution_count": 0,
      "source_expected_mapping_vector": [
        0,
        6,
        5,
        4,
        3,
        1,
        2
      ],
      "total_simulated_shots": 0
    },
    {
      "dataset_id": "r169_non_tie",
      "elapsed_ns": 26720,
      "exact_expected_mapping_vector": [
        0,
        6,
        5,
        4,
        3,
        1,
        2
      ],
      "expected_mapping_vector": [
        0,
        6,
        5,
        4,
        3,
        1,
        2
      ],
      "kind": "standard",
      "mapping_vector": [
        0,
        6,
        5,
        4,
        3,
        1,
        2
      ],
      "matches_expected": true,
      "policy": "rust_biguint_exact_retained_binary64",
      "profile_id": "ascending_sorted_order",
      "replay_index": 26,
      "row_hash": "8150abc46b774ab2fb0aef496e56fef525e9c5bd1baf97098077d56a001d2977",
      "simulation_execution_count": 0,
      "source_expected_mapping_vector": [
        0,
        6,
        5,
        4,
        3,
        1,
        2
      ],
      "total_simulated_shots": 0
    },
    {
      "dataset_id": "r169_non_tie",
      "elapsed_ns": 26881,
      "exact_expected_mapping_vector": [
        0,
        6,
        5,
        4,
        3,
        1,
        2
      ],
      "expected_mapping_vector": [
        0,
        6,
        5,
        4,
        3,
        1,
        2
      ],
      "kind": "standard",
      "mapping_vector": [
        0,
        6,
        5,
        4,
        3,
        1,
        2
      ],
      "matches_expected": true,
      "policy": "rust_biguint_exact_retained_binary64",
      "profile_id": "ascending_sorted_order",
      "replay_index": 27,
      "row_hash": "2ca387d4c9b345f3c08856be58551c75294716d5966a4d7440dabbbb9d6746b2",
      "simulation_execution_count": 0,
      "source_expected_mapping_vector": [
        0,
        6,
        5,
        4,
        3,
        1,
        2
      ],
      "total_simulated_shots": 0
    },
    {
      "dataset_id": "r169_non_tie",
      "elapsed_ns": 25778,
      "exact_expected_mapping_vector": [
        0,
        6,
        5,
        4,
        3,
        1,
        2
      ],
      "expected_mapping_vector": [
        0,
        6,
        5,
        4,
        3,
        1,
        2
      ],
      "kind": "standard",
      "mapping_vector": [
        0,
        6,
        5,
        4,
        3,
        1,
        2
      ],
      "matches_expected": true,
      "policy": "rust_biguint_exact_retained_binary64",
      "profile_id": "ascending_sorted_order",
      "replay_index": 28,
      "row_hash": "73f6374ab9d9a73f1173061101082658d9c5d108ed2f131a78f210d14c6575a4",
      "simulation_execution_count": 0,
      "source_expected_mapping_vector": [
        0,
        6,
        5,
        4,
        3,
        1,
        2
      ],
      "total_simulated_shots": 0
    },
    {
      "dataset_id": "r169_non_tie",
      "elapsed_ns": 26089,
      "exact_expected_mapping_vector": [
        0,
        6,
        5,
        4,
        3,
        1,
        2
      ],
      "expected_mapping_vector": [
        0,
        6,
        5,
        4,
        3,
        1,
        2
      ],
      "kind": "standard",
      "mapping_vector": [
        0,
        6,
        5,
        4,
        3,
        1,
        2
      ],
      "matches_expected": true,
      "policy": "rust_biguint_exact_retained_binary64",
      "profile_id": "ascending_sorted_order",
      "replay_index": 29,
      "row_hash": "fdebeaec7f1331ade171bb1f3abd782292182bfc55f9dca7f469c1ddff37fd93",
      "simulation_execution_count": 0,
      "source_expected_mapping_vector": [
        0,
        6,
        5,
        4,
        3,
        1,
        2
      ],
      "total_simulated_shots": 0
    },
    {
      "dataset_id": "r169_non_tie",
      "elapsed_ns": 30207,
      "exact_expected_mapping_vector": [
        0,
        6,
        5,
        4,
        3,
        1,
        2
      ],
      "expected_mapping_vector": [
        0,
        6,
        5,
        4,
        3,
        1,
        2
      ],
      "kind": "standard",
      "mapping_vector": [
        0,
        6,
        5,
        4,
        3,
        1,
        2
      ],
      "matches_expected": true,
      "policy": "rust_biguint_exact_retained_binary64",
      "profile_id": "ascending_sorted_order",
      "replay_index": 30,
      "row_hash": "1654fe0c2062786b93ce13062fad4b149fe39183380b431ee0490d10b2a17c55",
      "simulation_execution_count": 0,
      "source_expected_mapping_vector": [
        0,
        6,
        5,
        4,
        3,
        1,
        2
      ],
      "total_simulated_shots": 0
    },
    {
      "dataset_id": "r169_non_tie",
      "elapsed_ns": 26800,
      "exact_expected_mapping_vector": [
        0,
        6,
        5,
        4,
        3,
        1,
        2
      ],
      "expected_mapping_vector": [
        0,
        6,
        5,
        4,
        3,
        1,
        2
      ],
      "kind": "standard",
      "mapping_vector": [
        0,
        6,
        5,
        4,
        3,
        1,
        2
      ],
      "matches_expected": true,
      "policy": "rust_biguint_exact_retained_binary64",
      "profile_id": "ascending_sorted_order",
      "replay_index": 31,
      "row_hash": "9cd568f7b03b29066affe853cf9f58290b09fabf9f98ae68500a2fab2dcc4b7e",
      "simulation_execution_count": 0,
      "source_expected_mapping_vector": [
        0,
        6,
        5,
        4,
        3,
        1,
        2
      ],
      "total_simulated_shots": 0
    },
    {
      "dataset_id": "r169_non_tie",
      "elapsed_ns": 26249,
      "exact_expected_mapping_vector": [
        0,
        6,
        5,
        4,
        3,
        1,
        2
      ],
      "expected_mapping_vector": [
        0,
        6,
        5,
        4,
        3,
        1,
        2
      ],
      "kind": "standard",
      "mapping_vector": [
        0,
        6,
        5,
        4,
        3,
        1,
        2
      ],
      "matches_expected": true,
      "policy": "rust_biguint_exact_retained_binary64",
      "profile_id": "ascending_sorted_order",
      "replay_index": 32,
      "row_hash": "f75ed47f3bcc55366f6639eb810d855ea51e3c2dd276d1904b338638e923a92f",
      "simulation_execution_count": 0,
      "source_expected_mapping_vector": [
        0,
        6,
        5,
        4,
        3,
        1,
        2
      ],
      "total_simulated_shots": 0
    },
    {
      "dataset_id": "r169_non_tie",
      "elapsed_ns": 25929,
      "exact_expected_mapping_vector": [
        0,
        6,
        5,
        4,
        3,
        1,
        2
      ],
      "expected_mapping_vector": [
        0,
        6,
        5,
        4,
        3,
        1,
        2
      ],
      "kind": "standard",
      "mapping_vector": [
        0,
        6,
        5,
        4,
        3,
        1,
        2
      ],
      "matches_expected": true,
      "policy": "rust_biguint_exact_retained_binary64",
      "profile_id": "ascending_sorted_order",
      "replay_index": 33,
      "row_hash": "0ba047c4a63f5da9226f7b365247ca21ff87bf3b476792168ee584acd61fc7a2",
      "simulation_execution_count": 0,
      "source_expected_mapping_vector": [
        0,
        6,
        5,
        4,
        3,
        1,
        2
      ],
      "total_simulated_shots": 0
    },
    {
      "dataset_id": "r169_non_tie",
      "elapsed_ns": 26088,
      "exact_expected_mapping_vector": [
        0,
        6,
        5,
        4,
        3,
        1,
        2
      ],
      "expected_mapping_vector": [
        0,
        6,
        5,
        4,
        3,
        1,
        2
      ],
      "kind": "standard",
      "mapping_vector": [
        0,
        6,
        5,
        4,
        3,
        1,
        2
      ],
      "matches_expected": true,
      "policy": "rust_biguint_exact_retained_binary64",
      "profile_id": "ascending_sorted_order",
      "replay_index": 34,
      "row_hash": "cb4876874fb729c4dc8d2860f5cb1e0ee0702a71a0fa4aa17ce0db0e3722e7f7",
      "simulation_execution_count": 0,
      "source_expected_mapping_vector": [
        0,
        6,
        5,
        4,
        3,
        1,
        2
      ],
      "total_simulated_shots": 0
    },
    {
      "dataset_id": "r169_non_tie",
      "elapsed_ns": 25788,
      "exact_expected_mapping_vector": [
        0,
        6,
        5,
        4,
        3,
        1,
        2
      ],
      "expected_mapping_vector": [
        0,
        6,
        5,
        4,
        3,
        1,
        2
      ],
      "kind": "standard",
      "mapping_vector": [
        0,
        6,
        5,
        4,
        3,
        1,
        2
      ],
      "matches_expected": true,
      "policy": "rust_biguint_exact_retained_binary64",
      "profile_id": "ascending_sorted_order",
      "replay_index": 35,
      "row_hash": "2e28646ae2636221f2cfbe9712bafaecba23ff0fe53fc397406f821685434254",
      "simulation_execution_count": 0,
      "source_expected_mapping_vector": [
        0,
        6,
        5,
        4,
        3,
        1,
        2
      ],
      "total_simulated_shots": 0
    },
    {
      "dataset_id": "r169_non_tie",
      "elapsed_ns": 25567,
      "exact_expected_mapping_vector": [
        0,
        6,
        5,
        4,
        3,
        1,
        2
      ],
      "expected_mapping_vector": [
        0,
        6,
        5,
        4,
        3,
        1,
        2
      ],
      "kind": "standard",
      "mapping_vector": [
        0,
        6,
        5,
        4,
        3,
        1,
        2
      ],
      "matches_expected": true,
      "policy": "rust_biguint_exact_retained_binary64",
      "profile_id": "ascending_sorted_order",
      "replay_index": 36,
      "row_hash": "73a8fe1ffdddf46fadd193006ed296051ef9da557ec1f6ca58e5170db23e2a61",
      "simulation_execution_count": 0,
      "source_expected_mapping_vector": [
        0,
        6,
        5,
        4,
        3,
        1,
        2
      ],
      "total_simulated_shots": 0
    },
    {
      "dataset_id": "r169_non_tie",
      "elapsed_ns": 25949,
      "exact_expected_mapping_vector": [
        0,
        6,
        5,
        4,
        3,
        1,
        2
      ],
      "expected_mapping_vector": [
        0,
        6,
        5,
        4,
        3,
        1,
        2
      ],
      "kind": "standard",
      "mapping_vector": [
        0,
        6,
        5,
        4,
        3,
        1,
        2
      ],
      "matches_expected": true,
      "policy": "rust_biguint_exact_retained_binary64",
      "profile_id": "ascending_sorted_order",
      "replay_index": 37,
      "row_hash": "d95cff6c010904d2f5332c80b51b0c3f7b27638adaa0406ac7de7844aba4a5d0",
      "simulation_execution_count": 0,
      "source_expected_mapping_vector": [
        0,
        6,
        5,
        4,
        3,
        1,
        2
      ],
      "total_simulated_shots": 0
    },
    {
      "dataset_id": "r169_non_tie",
      "elapsed_ns": 25687,
      "exact_expected_mapping_vector": [
        0,
        6,
        5,
        4,
        3,
        1,
        2
      ],
      "expected_mapping_vector": [
        0,
        6,
        5,
        4,
        3,
        1,
        2
      ],
      "kind": "standard",
      "mapping_vector": [
        0,
        6,
        5,
        4,
        3,
        1,
        2
      ],
      "matches_expected": true,
      "policy": "rust_biguint_exact_retained_binary64",
      "profile_id": "ascending_sorted_order",
      "replay_index": 38,
      "row_hash": "79f0b26b0507ce35cc3530d6841dfa1414e1a1ae76330d84114bfe8e6be29b80",
      "simulation_execution_count": 0,
      "source_expected_mapping_vector": [
        0,
        6,
        5,
        4,
        3,
        1,
        2
      ],
      "total_simulated_shots": 0
    },
    {
      "dataset_id": "r169_non_tie",
      "elapsed_ns": 25678,
      "exact_expected_mapping_vector": [
        0,
        6,
        5,
        4,
        3,
        1,
        2
      ],
      "expected_mapping_vector": [
        0,
        6,
        5,
        4,
        3,
        1,
        2
      ],
      "kind": "standard",
      "mapping_vector": [
        0,
        6,
        5,
        4,
        3,
        1,
        2
      ],
      "matches_expected": true,
      "policy": "rust_biguint_exact_retained_binary64",
      "profile_id": "ascending_sorted_order",
      "replay_index": 39,
      "row_hash": "5d156c9d52687e5385b033b5430c4102cb00e60b6790f2dd6de6be52390a43af",
      "simulation_execution_count": 0,
      "source_expected_mapping_vector": [
        0,
        6,
        5,
        4,
        3,
        1,
        2
      ],
      "total_simulated_shots": 0
    },
    {
      "dataset_id": "r169_non_tie",
      "elapsed_ns": 25578,
      "exact_expected_mapping_vector": [
        0,
        6,
        5,
        4,
        3,
        1,
        2
      ],
      "expected_mapping_vector": [
        0,
        6,
        5,
        4,
        3,
        1,
        2
      ],
      "kind": "standard",
      "mapping_vector": [
        0,
        6,
        5,
        4,
        3,
        1,
        2
      ],
      "matches_expected": true,
      "policy": "rust_biguint_exact_retained_binary64",
      "profile_id": "ascending_sorted_order",
      "replay_index": 40,
      "row_hash": "a9bc3979539fa22770a7db07496b4870c96f52d03d5564c6d5293af7956015a9",
      "simulation_execution_count": 0,
      "source_expected_mapping_vector": [
        0,
        6,
        5,
        4,
        3,
        1,
        2
      ],
      "total_simulated_shots": 0
    },
    {
      "dataset_id": "r169_non_tie",
      "elapsed_ns": 26530,
      "exact_expected_mapping_vector": [
        0,
        6,
        5,
        4,
        3,
        1,
        2
      ],
      "expected_mapping_vector": [
        0,
        6,
        5,
        4,
        3,
        1,
        2
      ],
      "kind": "standard",
      "mapping_vector": [
        0,
        6,
        5,
        4,
        3,
        1,
        2
      ],
      "matches_expected": true,
      "policy": "rust_biguint_exact_retained_binary64",
      "profile_id": "ascending_sorted_order",
      "replay_index": 41,
      "row_hash": "a1b2d3bb4eccf6d8d119050b8f831a0b2893b528313890d32e1d7f6617af2b3b",
      "simulation_execution_count": 0,
      "source_expected_mapping_vector": [
        0,
        6,
        5,
        4,
        3,
        1,
        2
      ],
      "total_simulated_shots": 0
    },
    {
      "dataset_id": "r169_non_tie",
      "elapsed_ns": 25948,
      "exact_expected_mapping_vector": [
        0,
        6,
        5,
        4,
        3,
        1,
        2
      ],
      "expected_mapping_vector": [
        0,
        6,
        5,
        4,
        3,
        1,
        2
      ],
      "kind": "standard",
      "mapping_vector": [
        0,
        6,
        5,
        4,
        3,
        1,
        2
      ],
      "matches_expected": true,
      "policy": "rust_biguint_exact_retained_binary64",
      "profile_id": "ascending_sorted_order",
      "replay_index": 42,
      "row_hash": "663207ce2c87675d53c666f1c3e5f38f72ec0924d859b86eb7a871c8e51927f6",
      "simulation_execution_count": 0,
      "source_expected_mapping_vector": [
        0,
        6,
        5,
        4,
        3,
        1,
        2
      ],
      "total_simulated_shots": 0
    },
    {
      "dataset_id": "r169_non_tie",
      "elapsed_ns": 26049,
      "exact_expected_mapping_vector": [
        0,
        6,
        5,
        4,
        3,
        1,
        2
      ],
      "expected_mapping_vector": [
        0,
        6,
        5,
        4,
        3,
        1,
        2
      ],
      "kind": "standard",
      "mapping_vector": [
        0,
        6,
        5,
        4,
        3,
        1,
        2
      ],
      "matches_expected": true,
      "policy": "rust_biguint_exact_retained_binary64",
      "profile_id": "ascending_sorted_order",
      "replay_index": 43,
      "row_hash": "5080bc4c62373f69c21630f051e4f058b707d611ba621db25a7edccdd7509603",
      "simulation_execution_count": 0,
      "source_expected_mapping_vector": [
        0,
        6,
        5,
        4,
        3,
        1,
        2
      ],
      "total_simulated_shots": 0
    },
    {
      "dataset_id": "r169_non_tie",
      "elapsed_ns": 25467,
      "exact_expected_mapping_vector": [
        0,
        6,
        5,
        4,
        3,
        1,
        2
      ],
      "expected_mapping_vector": [
        0,
        6,
        5,
        4,
        3,
        1,
        2
      ],
      "kind": "standard",
      "mapping_vector": [
        0,
        6,
        5,
        4,
        3,
        1,
        2
      ],
      "matches_expected": true,
      "policy": "rust_biguint_exact_retained_binary64",
      "profile_id": "ascending_sorted_order",
      "replay_index": 44,
      "row_hash": "40311ea41fbc7a4cb7bfd7cadb41d904b9fe4b3840130ff990635cbb4e7f940e",
      "simulation_execution_count": 0,
      "source_expected_mapping_vector": [
        0,
        6,
        5,
        4,
        3,
        1,
        2
      ],
      "total_simulated_shots": 0
    },
    {
      "dataset_id": "r169_non_tie",
      "elapsed_ns": 26049,
      "exact_expected_mapping_vector": [
        0,
        6,
        5,
        4,
        3,
        1,
        2
      ],
      "expected_mapping_vector": [
        0,
        6,
        5,
        4,
        3,
        1,
        2
      ],
      "kind": "standard",
      "mapping_vector": [
        0,
        6,
        5,
        4,
        3,
        1,
        2
      ],
      "matches_expected": true,
      "policy": "rust_biguint_exact_retained_binary64",
      "profile_id": "ascending_sorted_order",
      "replay_index": 45,
      "row_hash": "45d92e494c495c4236a42bfc6d9cdc8980ff64ba3944ee048e0ef1f91ed903fd",
      "simulation_execution_count": 0,
      "source_expected_mapping_vector": [
        0,
        6,
        5,
        4,
        3,
        1,
        2
      ],
      "total_simulated_shots": 0
    },
    {
      "dataset_id": "r169_non_tie",
      "elapsed_ns": 25938,
      "exact_expected_mapping_vector": [
        0,
        6,
        5,
        4,
        3,
        1,
        2
      ],
      "expected_mapping_vector": [
        0,
        6,
        5,
        4,
        3,
        1,
        2
      ],
      "kind": "standard",
      "mapping_vector": [
        0,
        6,
        5,
        4,
        3,
        1,
        2
      ],
      "matches_expected": true,
      "policy": "rust_biguint_exact_retained_binary64",
      "profile_id": "ascending_sorted_order",
      "replay_index": 46,
      "row_hash": "b75e007b55c77c8f05ba5b1dff0feff43f781f1acc19f36de89f5a24ad2d4e72",
      "simulation_execution_count": 0,
      "source_expected_mapping_vector": [
        0,
        6,
        5,
        4,
        3,
        1,
        2
      ],
      "total_simulated_shots": 0
    },
    {
      "dataset_id": "r169_non_tie",
      "elapsed_ns": 25527,
      "exact_expected_mapping_vector": [
        0,
        6,
        5,
        4,
        3,
        1,
        2
      ],
      "expected_mapping_vector": [
        0,
        6,
        5,
        4,
        3,
        1,
        2
      ],
      "kind": "standard",
      "mapping_vector": [
        0,
        6,
        5,
        4,
        3,
        1,
        2
      ],
      "matches_expected": true,
      "policy": "rust_biguint_exact_retained_binary64",
      "profile_id": "ascending_sorted_order",
      "replay_index": 47,
      "row_hash": "d8ecc349774c8b908ec6a77253b4e5e0d9b27d4cf5020499e664d0476b4e1511",
      "simulation_execution_count": 0,
      "source_expected_mapping_vector": [
        0,
        6,
        5,
        4,
        3,
        1,
        2
      ],
      "total_simulated_shots": 0
    },
    {
      "dataset_id": "r169_non_tie",
      "elapsed_ns": 30257,
      "exact_expected_mapping_vector": [
        0,
        6,
        5,
        4,
        3,
        1,
        2
      ],
      "expected_mapping_vector": [
        0,
        6,
        5,
        4,
        3,
        1,
        2
      ],
      "kind": "standard",
      "mapping_vector": [
        0,
        6,
        5,
        4,
        3,
        1,
        2
      ],
      "matches_expected": true,
      "policy": "rust_biguint_exact_retained_binary64",
      "profile_id": "ascending_sorted_order",
      "replay_index": 48,
      "row_hash": "73a31b1a3edd8f4c34f24e84c29c181e7733f99e9ba730816424c94c76f4fc81",
      "simulation_execution_count": 0,
      "source_expected_mapping_vector": [
        0,
        6,
        5,
        4,
        3,
        1,
        2
      ],
      "total_simulated_shots": 0
    },
    {
      "dataset_id": "r169_non_tie",
      "elapsed_ns": 26119,
      "exact_expected_mapping_vector": [
        0,
        6,
        5,
        4,
        3,
        1,
        2
      ],
      "expected_mapping_vector": [
        0,
        6,
        5,
        4,
        3,
        1,
        2
      ],
      "kind": "standard",
      "mapping_vector": [
        0,
        6,
        5,
        4,
        3,
        1,
        2
      ],
      "matches_expected": true,
      "policy": "rust_biguint_exact_retained_binary64",
      "profile_id": "ascending_sorted_order",
      "replay_index": 49,
      "row_hash": "145a883cb690fc56cab5af572fa79b7ffd2653892008478d7a4bffab86e8960f",
      "simulation_execution_count": 0,
      "source_expected_mapping_vector": [
        0,
        6,
        5,
        4,
        3,
        1,
        2
      ],
      "total_simulated_shots": 0
    },
    {
      "dataset_id": "r169_non_tie",
      "elapsed_ns": 25447,
      "exact_expected_mapping_vector": [
        0,
        6,
        5,
        4,
        3,
        1,
        2
      ],
      "expected_mapping_vector": [
        0,
        6,
        5,
        4,
        3,
        1,
        2
      ],
      "kind": "standard",
      "mapping_vector": [
        0,
        6,
        5,
        4,
        3,
        1,
        2
      ],
      "matches_expected": true,
      "policy": "rust_biguint_exact_retained_binary64",
      "profile_id": "ascending_sorted_order",
      "replay_index": 50,
      "row_hash": "0db0eaeb46957a67fdccdd3636e3695b5da4f6f7621ff7d664f346ebc93a3606",
      "simulation_execution_count": 0,
      "source_expected_mapping_vector": [
        0,
        6,
        5,
        4,
        3,
        1,
        2
      ],
      "total_simulated_shots": 0
    },
    {
      "dataset_id": "r169_non_tie",
      "elapsed_ns": 25578,
      "exact_expected_mapping_vector": [
        0,
        6,
        5,
        4,
        3,
        1,
        2
      ],
      "expected_mapping_vector": [
        0,
        6,
        5,
        4,
        3,
        1,
        2
      ],
      "kind": "standard",
      "mapping_vector": [
        0,
        6,
        5,
        4,
        3,
        1,
        2
      ],
      "matches_expected": true,
      "policy": "rust_biguint_exact_retained_binary64",
      "profile_id": "ascending_sorted_order",
      "replay_index": 51,
      "row_hash": "382ad8ccad87f5289b43a5f305dc8e4a2a8322e86be9126602dccb28bbc409d7",
      "simulation_execution_count": 0,
      "source_expected_mapping_vector": [
        0,
        6,
        5,
        4,
        3,
        1,
        2
      ],
      "total_simulated_shots": 0
    },
    {
      "dataset_id": "r169_non_tie",
      "elapsed_ns": 25517,
      "exact_expected_mapping_vector": [
        0,
        6,
        5,
        4,
        3,
        1,
        2
      ],
      "expected_mapping_vector": [
        0,
        6,
        5,
        4,
        3,
        1,
        2
      ],
      "kind": "standard",
      "mapping_vector": [
        0,
        6,
        5,
        4,
        3,
        1,
        2
      ],
      "matches_expected": true,
      "policy": "rust_biguint_exact_retained_binary64",
      "profile_id": "ascending_sorted_order",
      "replay_index": 52,
      "row_hash": "04760095ac89092e039c510f762aa858ad2f75d5b25589e27e8b23157ba8a124",
      "simulation_execution_count": 0,
      "source_expected_mapping_vector": [
        0,
        6,
        5,
        4,
        3,
        1,
        2
      ],
      "total_simulated_shots": 0
    },
    {
      "dataset_id": "r169_non_tie",
      "elapsed_ns": 25548,
      "exact_expected_mapping_vector": [
        0,
        6,
        5,
        4,
        3,
        1,
        2
      ],
      "expected_mapping_vector": [
        0,
        6,
        5,
        4,
        3,
        1,
        2
      ],
      "kind": "standard",
      "mapping_vector": [
        0,
        6,
        5,
        4,
        3,
        1,
        2
      ],
      "matches_expected": true,
      "policy": "rust_biguint_exact_retained_binary64",
      "profile_id": "ascending_sorted_order",
      "replay_index": 53,
      "row_hash": "31f29403999d1df9fbefb7044c9ac8f56de9a7dbc37aba3d1ffeb2635ad8e915",
      "simulation_execution_count": 0,
      "source_expected_mapping_vector": [
        0,
        6,
        5,
        4,
        3,
        1,
        2
      ],
      "total_simulated_shots": 0
    },
    {
      "dataset_id": "r169_non_tie",
      "elapsed_ns": 25407,
      "exact_expected_mapping_vector": [
        0,
        6,
        5,
        4,
        3,
        1,
        2
      ],
      "expected_mapping_vector": [
        0,
        6,
        5,
        4,
        3,
        1,
        2
      ],
      "kind": "standard",
      "mapping_vector": [
        0,
        6,
        5,
        4,
        3,
        1,
        2
      ],
      "matches_expected": true,
      "policy": "rust_biguint_exact_retained_binary64",
      "profile_id": "ascending_sorted_order",
      "replay_index": 54,
      "row_hash": "3c0c82b88c554281b566ff444eee1758abfff23c08c1fdfa2216161327892b4a",
      "simulation_execution_count": 0,
      "source_expected_mapping_vector": [
        0,
        6,
        5,
        4,
        3,
        1,
        2
      ],
      "total_simulated_shots": 0
    },
    {
      "dataset_id": "r169_non_tie",
      "elapsed_ns": 25808,
      "exact_expected_mapping_vector": [
        0,
        6,
        5,
        4,
        3,
        1,
        2
      ],
      "expected_mapping_vector": [
        0,
        6,
        5,
        4,
        3,
        1,
        2
      ],
      "kind": "standard",
      "mapping_vector": [
        0,
        6,
        5,
        4,
        3,
        1,
        2
      ],
      "matches_expected": true,
      "policy": "rust_biguint_exact_retained_binary64",
      "profile_id": "ascending_sorted_order",
      "replay_index": 55,
      "row_hash": "361ef2804b02e13dd3f0f1309b25896ea42b67e1ae982af6f4f5f3d9282ccf48",
      "simulation_execution_count": 0,
      "source_expected_mapping_vector": [
        0,
        6,
        5,
        4,
        3,
        1,
        2
      ],
      "total_simulated_shots": 0
    },
    {
      "dataset_id": "r169_non_tie",
      "elapsed_ns": 29875,
      "exact_expected_mapping_vector": [
        0,
        6,
        5,
        4,
        3,
        1,
        2
      ],
      "expected_mapping_vector": [
        0,
        6,
        5,
        4,
        3,
        1,
        2
      ],
      "kind": "standard",
      "mapping_vector": [
        0,
        6,
        5,
        4,
        3,
        1,
        2
      ],
      "matches_expected": true,
      "policy": "rust_biguint_exact_retained_binary64",
      "profile_id": "ascending_sorted_order",
      "replay_index": 56,
      "row_hash": "c308f53f761ddf619441211adf4444937ea3a7902a772159cb6b8b24bb908e74",
      "simulation_execution_count": 0,
      "source_expected_mapping_vector": [
        0,
        6,
        5,
        4,
        3,
        1,
        2
      ],
      "total_simulated_shots": 0
    },
    {
      "dataset_id": "r169_non_tie",
      "elapsed_ns": 26610,
      "exact_expected_mapping_vector": [
        0,
        6,
        5,
        4,
        3,
        1,
        2
      ],
      "expected_mapping_vector": [
        0,
        6,
        5,
        4,
        3,
        1,
        2
      ],
      "kind": "standard",
      "mapping_vector": [
        0,
        6,
        5,
        4,
        3,
        1,
        2
      ],
      "matches_expected": true,
      "policy": "rust_biguint_exact_retained_binary64",
      "profile_id": "ascending_sorted_order",
      "replay_index": 57,
      "row_hash": "e5999b63293f651585b9719627f873f5225da1ac303476f626a3fc32f58214c4",
      "simulation_execution_count": 0,
      "source_expected_mapping_vector": [
        0,
        6,
        5,
        4,
        3,
        1,
        2
      ],
      "total_simulated_shots": 0
    },
    {
      "dataset_id": "r169_non_tie",
      "elapsed_ns": 26018,
      "exact_expected_mapping_vector": [
        0,
        6,
        5,
        4,
        3,
        1,
        2
      ],
      "expected_mapping_vector": [
        0,
        6,
        5,
        4,
        3,
        1,
        2
      ],
      "kind": "standard",
      "mapping_vector": [
        0,
        6,
        5,
        4,
        3,
        1,
        2
      ],
      "matches_expected": true,
      "policy": "rust_biguint_exact_retained_binary64",
      "profile_id": "ascending_sorted_order",
      "replay_index": 58,
      "row_hash": "8f35e6e7257d721dab9ac43bdfad3d4935ae7a5ca95176cd13dc59482fae1c28",
      "simulation_execution_count": 0,
      "source_expected_mapping_vector": [
        0,
        6,
        5,
        4,
        3,
        1,
        2
      ],
      "total_simulated_shots": 0
    },
    {
      "dataset_id": "r169_non_tie",
      "elapsed_ns": 25678,
      "exact_expected_mapping_vector": [
        0,
        6,
        5,
        4,
        3,
        1,
        2
      ],
      "expected_mapping_vector": [
        0,
        6,
        5,
        4,
        3,
        1,
        2
      ],
      "kind": "standard",
      "mapping_vector": [
        0,
        6,
        5,
        4,
        3,
        1,
        2
      ],
      "matches_expected": true,
      "policy": "rust_biguint_exact_retained_binary64",
      "profile_id": "ascending_sorted_order",
      "replay_index": 59,
      "row_hash": "4b4d4ded72fe9e5d31c9c4145a0a9501bcf2de9712b9f10aa967065d06b6bf5b",
      "simulation_execution_count": 0,
      "source_expected_mapping_vector": [
        0,
        6,
        5,
        4,
        3,
        1,
        2
      ],
      "total_simulated_shots": 0
    },
    {
      "dataset_id": "r169_non_tie",
      "elapsed_ns": 25637,
      "exact_expected_mapping_vector": [
        0,
        6,
        5,
        4,
        3,
        1,
        2
      ],
      "expected_mapping_vector": [
        0,
        6,
        5,
        4,
        3,
        1,
        2
      ],
      "kind": "standard",
      "mapping_vector": [
        0,
        6,
        5,
        4,
        3,
        1,
        2
      ],
      "matches_expected": true,
      "policy": "rust_biguint_exact_retained_binary64",
      "profile_id": "ascending_sorted_order",
      "replay_index": 60,
      "row_hash": "23444cea5d95afa0ee8e56d6c3d4f87f0f423fa6c6456485cead429bec7c3561",
      "simulation_execution_count": 0,
      "source_expected_mapping_vector": [
        0,
        6,
        5,
        4,
        3,
        1,
        2
      ],
      "total_simulated_shots": 0
    },
    {
      "dataset_id": "r169_non_tie",
      "elapsed_ns": 25678,
      "exact_expected_mapping_vector": [
        0,
        6,
        5,
        4,
        3,
        1,
        2
      ],
      "expected_mapping_vector": [
        0,
        6,
        5,
        4,
        3,
        1,
        2
      ],
      "kind": "standard",
      "mapping_vector": [
        0,
        6,
        5,
        4,
        3,
        1,
        2
      ],
      "matches_expected": true,
      "policy": "rust_biguint_exact_retained_binary64",
      "profile_id": "ascending_sorted_order",
      "replay_index": 61,
      "row_hash": "aae889c8704d8aae41040f0ed0233fde7c573890cff23e9f706a0493c4ebcc44",
      "simulation_execution_count": 0,
      "source_expected_mapping_vector": [
        0,
        6,
        5,
        4,
        3,
        1,
        2
      ],
      "total_simulated_shots": 0
    },
    {
      "dataset_id": "r169_non_tie",
      "elapsed_ns": 26029,
      "exact_expected_mapping_vector": [
        0,
        6,
        5,
        4,
        3,
        1,
        2
      ],
      "expected_mapping_vector": [
        0,
        6,
        5,
        4,
        3,
        1,
        2
      ],
      "kind": "standard",
      "mapping_vector": [
        0,
        6,
        5,
        4,
        3,
        1,
        2
      ],
      "matches_expected": true,
      "policy": "rust_biguint_exact_retained_binary64",
      "profile_id": "ascending_sorted_order",
      "replay_index": 62,
      "row_hash": "2da13841d3507cf7a3a969656bd5b62edd3800907326bac32ac97d680034d108",
      "simulation_execution_count": 0,
      "source_expected_mapping_vector": [
        0,
        6,
        5,
        4,
        3,
        1,
        2
      ],
      "total_simulated_shots": 0
    },
    {
      "dataset_id": "r169_non_tie",
      "elapsed_ns": 25818,
      "exact_expected_mapping_vector": [
        0,
        6,
        5,
        4,
        3,
        1,
        2
      ],
      "expected_mapping_vector": [
        0,
        6,
        5,
        4,
        3,
        1,
        2
      ],
      "kind": "standard",
      "mapping_vector": [
        0,
        6,
        5,
        4,
        3,
        1,
        2
      ],
      "matches_expected": true,
      "policy": "rust_biguint_exact_retained_binary64",
      "profile_id": "ascending_sorted_order",
      "replay_index": 63,
      "row_hash": "4d92f516b62fc895553c1f22f245bbd3935b501972ddf27786b61dcf8f417459",
      "simulation_execution_count": 0,
      "source_expected_mapping_vector": [
        0,
        6,
        5,
        4,
        3,
        1,
        2
      ],
      "total_simulated_shots": 0
    }
  ],
  "simulation_execution_count": 0,
  "source_worker_path": "results/B4_B8_R169_target_compatible_candidate_replay/ascending_sorted_order.json",
  "source_worker_sha256": "a07f053a1a0ab4b537a490858f402fc061529c88d0e32030fdf914fe1f9ce8c9",
  "started_at_unix": 1784563308,
  "target_descriptor_sha256": "702c8fd9dcf67a069e7af63e31a57c74c17aaa5e3c5b6d8c2e28ec0c049c0de7",
  "total_simulated_shots": 0,
  "warmup_call_count": 16,
  "warmup_matches_expected": 16
}
