{
  "accelerator_path": "/tmp/prometheus-r176-overlay-0469ab075ef40a84/qiskit/_accelerate.abi3.so",
  "accelerator_sha256": "0469ab075ef40a841da017e2b9cebeac5fe2c1ac8fc95b77c99dc773ea3ff054",
  "contract_payload_hash": "1612b5140aecb82024f8db34a12df87fcdcc9e4989f013a82eac3b4cae6cd96e",
  "dataset_id": "r169_non_tie",
  "elapsed_ns_median": 14126.5,
  "elapsed_ns_p95_nearest_rank": 18113,
  "environment": {
    "github_run_attempt": "1",
    "github_run_id": "29757057658",
    "machine": "x86_64",
    "platform": "Linux-6.17.0-1020-azure-x86_64-with-glibc2.39",
    "python": "3.12.13",
    "pythonpath_head": "/home/runner/work/Prometheus-plan/Prometheus-plan/tools",
    "qiskit": "2.4.1",
    "qiskit_aer": "0.17.2",
    "qiskit_ibm_runtime": "0.46.1",
    "system": "Linux"
  },
  "identity": "r169_non_tie__descending_sorted_order",
  "input_qasm_sha256": "d6895b30e27cc9f75e93edffef348d1701526c077ba1121094c394b38fb68fb7",
  "kind": "standard",
  "manifest_hash": "b6e5a593e7ad841aa44c6af66a4b44081f759800f6033d8ec56ceb504e63f0a8",
  "peak_rss": 213996,
  "peak_rss_unit": "kibibytes",
  "policy": "source_f64",
  "preregistration": {
    "commit": "f4e99da05d9e1211fcb3a239144d6355f5cd8055",
    "created_at": "2026-07-20T15:50:41Z",
    "discussion": "https://github.com/crystal-tensor/Prometheus-plan/discussions/268"
  },
  "process_id": 10816,
  "process_instance_uuid": "45ada4d2-1632-456e-81d3-bffcbbed80e0",
  "profile_id": "descending_sorted_order",
  "protocol_payload_hash": "4c4899bb0e65de1387585ae034b884bb5508b5d01bf7775d670b65a7360b536d",
  "recorded_call_count": 64,
  "recorded_matches_expected": 64,
  "replay_rows": [
    {
      "dataset_id": "r169_non_tie",
      "elapsed_ns": 16160,
      "exact_expected_mapping_vector": [
        0,
        6,
        5,
        4,
        3,
        1,
        2
      ],
      "expected_mapping_vector": [
        0,
        6,
        5,
        4,
        3,
        1,
        2
      ],
      "kind": "standard",
      "mapping_vector": [
        0,
        6,
        5,
        4,
        3,
        1,
        2
      ],
      "matches_expected": true,
      "policy": "source_f64",
      "profile_id": "descending_sorted_order",
      "replay_index": 0,
      "row_hash": "dc3fbeddb00fa9377c457ff9048cd22ec196dc9e40c40b8574a7bda6301230b7",
      "simulation_execution_count": 0,
      "source_expected_mapping_vector": [
        0,
        6,
        5,
        4,
        3,
        1,
        2
      ],
      "total_simulated_shots": 0
    },
    {
      "dataset_id": "r169_non_tie",
      "elapsed_ns": 18695,
      "exact_expected_mapping_vector": [
        0,
        6,
        5,
        4,
        3,
        1,
        2
      ],
      "expected_mapping_vector": [
        0,
        6,
        5,
        4,
        3,
        1,
        2
      ],
      "kind": "standard",
      "mapping_vector": [
        0,
        6,
        5,
        4,
        3,
        1,
        2
      ],
      "matches_expected": true,
      "policy": "source_f64",
      "profile_id": "descending_sorted_order",
      "replay_index": 1,
      "row_hash": "e9c7f8d782079e32a033730b7b83c64f772c44d71a435311969b393d37485f61",
      "simulation_execution_count": 0,
      "source_expected_mapping_vector": [
        0,
        6,
        5,
        4,
        3,
        1,
        2
      ],
      "total_simulated_shots": 0
    },
    {
      "dataset_id": "r169_non_tie",
      "elapsed_ns": 16851,
      "exact_expected_mapping_vector": [
        0,
        6,
        5,
        4,
        3,
        1,
        2
      ],
      "expected_mapping_vector": [
        0,
        6,
        5,
        4,
        3,
        1,
        2
      ],
      "kind": "standard",
      "mapping_vector": [
        0,
        6,
        5,
        4,
        3,
        1,
        2
      ],
      "matches_expected": true,
      "policy": "source_f64",
      "profile_id": "descending_sorted_order",
      "replay_index": 2,
      "row_hash": "259800e8aad1ac91bbc2f73510dfd26a9c1c1ca75dc7b473ae02b8b7ea0a60f1",
      "simulation_execution_count": 0,
      "source_expected_mapping_vector": [
        0,
        6,
        5,
        4,
        3,
        1,
        2
      ],
      "total_simulated_shots": 0
    },
    {
      "dataset_id": "r169_non_tie",
      "elapsed_ns": 15499,
      "exact_expected_mapping_vector": [
        0,
        6,
        5,
        4,
        3,
        1,
        2
      ],
      "expected_mapping_vector": [
        0,
        6,
        5,
        4,
        3,
        1,
        2
      ],
      "kind": "standard",
      "mapping_vector": [
        0,
        6,
        5,
        4,
        3,
        1,
        2
      ],
      "matches_expected": true,
      "policy": "source_f64",
      "profile_id": "descending_sorted_order",
      "replay_index": 3,
      "row_hash": "98c36f745f2d1e22390be38a20e9290fc83782fcecb38237b480db0606fc11ba",
      "simulation_execution_count": 0,
      "source_expected_mapping_vector": [
        0,
        6,
        5,
        4,
        3,
        1,
        2
      ],
      "total_simulated_shots": 0
    },
    {
      "dataset_id": "r169_non_tie",
      "elapsed_ns": 15409,
      "exact_expected_mapping_vector": [
        0,
        6,
        5,
        4,
        3,
        1,
        2
      ],
      "expected_mapping_vector": [
        0,
        6,
        5,
        4,
        3,
        1,
        2
      ],
      "kind": "standard",
      "mapping_vector": [
        0,
        6,
        5,
        4,
        3,
        1,
        2
      ],
      "matches_expected": true,
      "policy": "source_f64",
      "profile_id": "descending_sorted_order",
      "replay_index": 4,
      "row_hash": "75dafc1af7d17f52731b989fcea38c3d893cd04c1825dc123b0d4a2e49f799e9",
      "simulation_execution_count": 0,
      "source_expected_mapping_vector": [
        0,
        6,
        5,
        4,
        3,
        1,
        2
      ],
      "total_simulated_shots": 0
    },
    {
      "dataset_id": "r169_non_tie",
      "elapsed_ns": 14737,
      "exact_expected_mapping_vector": [
        0,
        6,
        5,
        4,
        3,
        1,
        2
      ],
      "expected_mapping_vector": [
        0,
        6,
        5,
        4,
        3,
        1,
        2
      ],
      "kind": "standard",
      "mapping_vector": [
        0,
        6,
        5,
        4,
        3,
        1,
        2
      ],
      "matches_expected": true,
      "policy": "source_f64",
      "profile_id": "descending_sorted_order",
      "replay_index": 5,
      "row_hash": "881905aee4fd834af04fe4fa600b608ba8f3c0cdc34af3a2cae3bc3ceb8a7abe",
      "simulation_execution_count": 0,
      "source_expected_mapping_vector": [
        0,
        6,
        5,
        4,
        3,
        1,
        2
      ],
      "total_simulated_shots": 0
    },
    {
      "dataset_id": "r169_non_tie",
      "elapsed_ns": 14467,
      "exact_expected_mapping_vector": [
        0,
        6,
        5,
        4,
        3,
        1,
        2
      ],
      "expected_mapping_vector": [
        0,
        6,
        5,
        4,
        3,
        1,
        2
      ],
      "kind": "standard",
      "mapping_vector": [
        0,
        6,
        5,
        4,
        3,
        1,
        2
      ],
      "matches_expected": true,
      "policy": "source_f64",
      "profile_id": "descending_sorted_order",
      "replay_index": 6,
      "row_hash": "8075e3baee7c959659133c5e9509a8ca2f3411b431a6b583c0936718b488d6ba",
      "simulation_execution_count": 0,
      "source_expected_mapping_vector": [
        0,
        6,
        5,
        4,
        3,
        1,
        2
      ],
      "total_simulated_shots": 0
    },
    {
      "dataset_id": "r169_non_tie",
      "elapsed_ns": 16030,
      "exact_expected_mapping_vector": [
        0,
        6,
        5,
        4,
        3,
        1,
        2
      ],
      "expected_mapping_vector": [
        0,
        6,
        5,
        4,
        3,
        1,
        2
      ],
      "kind": "standard",
      "mapping_vector": [
        0,
        6,
        5,
        4,
        3,
        1,
        2
      ],
      "matches_expected": true,
      "policy": "source_f64",
      "profile_id": "descending_sorted_order",
      "replay_index": 7,
      "row_hash": "ff37c80461437f9abf0fe327c9a59f1517a62514d02a8b9d56ca12644ac81944",
      "simulation_execution_count": 0,
      "source_expected_mapping_vector": [
        0,
        6,
        5,
        4,
        3,
        1,
        2
      ],
      "total_simulated_shots": 0
    },
    {
      "dataset_id": "r169_non_tie",
      "elapsed_ns": 14557,
      "exact_expected_mapping_vector": [
        0,
        6,
        5,
        4,
        3,
        1,
        2
      ],
      "expected_mapping_vector": [
        0,
        6,
        5,
        4,
        3,
        1,
        2
      ],
      "kind": "standard",
      "mapping_vector": [
        0,
        6,
        5,
        4,
        3,
        1,
        2
      ],
      "matches_expected": true,
      "policy": "source_f64",
      "profile_id": "descending_sorted_order",
      "replay_index": 8,
      "row_hash": "810f58e502be24e1f9268d616e0fe9390649bfc6f8bcb23349f97955618ec5bc",
      "simulation_execution_count": 0,
      "source_expected_mapping_vector": [
        0,
        6,
        5,
        4,
        3,
        1,
        2
      ],
      "total_simulated_shots": 0
    },
    {
      "dataset_id": "r169_non_tie",
      "elapsed_ns": 14146,
      "exact_expected_mapping_vector": [
        0,
        6,
        5,
        4,
        3,
        1,
        2
      ],
      "expected_mapping_vector": [
        0,
        6,
        5,
        4,
        3,
        1,
        2
      ],
      "kind": "standard",
      "mapping_vector": [
        0,
        6,
        5,
        4,
        3,
        1,
        2
      ],
      "matches_expected": true,
      "policy": "source_f64",
      "profile_id": "descending_sorted_order",
      "replay_index": 9,
      "row_hash": "9a1b1615ab5381a060d478e487bd567d287b3bfde1e2ea4a33afef9ec2b30b3a",
      "simulation_execution_count": 0,
      "source_expected_mapping_vector": [
        0,
        6,
        5,
        4,
        3,
        1,
        2
      ],
      "total_simulated_shots": 0
    },
    {
      "dataset_id": "r169_non_tie",
      "elapsed_ns": 18113,
      "exact_expected_mapping_vector": [
        0,
        6,
        5,
        4,
        3,
        1,
        2
      ],
      "expected_mapping_vector": [
        0,
        6,
        5,
        4,
        3,
        1,
        2
      ],
      "kind": "standard",
      "mapping_vector": [
        0,
        6,
        5,
        4,
        3,
        1,
        2
      ],
      "matches_expected": true,
      "policy": "source_f64",
      "profile_id": "descending_sorted_order",
      "replay_index": 10,
      "row_hash": "16e64d6e05b59baf70ed404180a3c094c9a200606be17e29f1fd611f0aa45e9b",
      "simulation_execution_count": 0,
      "source_expected_mapping_vector": [
        0,
        6,
        5,
        4,
        3,
        1,
        2
      ],
      "total_simulated_shots": 0
    },
    {
      "dataset_id": "r169_non_tie",
      "elapsed_ns": 14857,
      "exact_expected_mapping_vector": [
        0,
        6,
        5,
        4,
        3,
        1,
        2
      ],
      "expected_mapping_vector": [
        0,
        6,
        5,
        4,
        3,
        1,
        2
      ],
      "kind": "standard",
      "mapping_vector": [
        0,
        6,
        5,
        4,
        3,
        1,
        2
      ],
      "matches_expected": true,
      "policy": "source_f64",
      "profile_id": "descending_sorted_order",
      "replay_index": 11,
      "row_hash": "5dbd2626499f08df5daf0aefbf6fd884fe03de35c57ef7d48168524df0c360e5",
      "simulation_execution_count": 0,
      "source_expected_mapping_vector": [
        0,
        6,
        5,
        4,
        3,
        1,
        2
      ],
      "total_simulated_shots": 0
    },
    {
      "dataset_id": "r169_non_tie",
      "elapsed_ns": 14737,
      "exact_expected_mapping_vector": [
        0,
        6,
        5,
        4,
        3,
        1,
        2
      ],
      "expected_mapping_vector": [
        0,
        6,
        5,
        4,
        3,
        1,
        2
      ],
      "kind": "standard",
      "mapping_vector": [
        0,
        6,
        5,
        4,
        3,
        1,
        2
      ],
      "matches_expected": true,
      "policy": "source_f64",
      "profile_id": "descending_sorted_order",
      "replay_index": 12,
      "row_hash": "3e753705c7e7f3c519a85d352b4a5eb2894572fd431d45ca13bfdffc355b954d",
      "simulation_execution_count": 0,
      "source_expected_mapping_vector": [
        0,
        6,
        5,
        4,
        3,
        1,
        2
      ],
      "total_simulated_shots": 0
    },
    {
      "dataset_id": "r169_non_tie",
      "elapsed_ns": 14297,
      "exact_expected_mapping_vector": [
        0,
        6,
        5,
        4,
        3,
        1,
        2
      ],
      "expected_mapping_vector": [
        0,
        6,
        5,
        4,
        3,
        1,
        2
      ],
      "kind": "standard",
      "mapping_vector": [
        0,
        6,
        5,
        4,
        3,
        1,
        2
      ],
      "matches_expected": true,
      "policy": "source_f64",
      "profile_id": "descending_sorted_order",
      "replay_index": 13,
      "row_hash": "cd7bc6a62753f79df922cb5934af5c406f796c408ed9cdd84e4914a212125350",
      "simulation_execution_count": 0,
      "source_expected_mapping_vector": [
        0,
        6,
        5,
        4,
        3,
        1,
        2
      ],
      "total_simulated_shots": 0
    },
    {
      "dataset_id": "r169_non_tie",
      "elapsed_ns": 14577,
      "exact_expected_mapping_vector": [
        0,
        6,
        5,
        4,
        3,
        1,
        2
      ],
      "expected_mapping_vector": [
        0,
        6,
        5,
        4,
        3,
        1,
        2
      ],
      "kind": "standard",
      "mapping_vector": [
        0,
        6,
        5,
        4,
        3,
        1,
        2
      ],
      "matches_expected": true,
      "policy": "source_f64",
      "profile_id": "descending_sorted_order",
      "replay_index": 14,
      "row_hash": "a5fa152786b56fba6928ae0663c0c1ec8aa057b6a1798b589e83e4f031a76a67",
      "simulation_execution_count": 0,
      "source_expected_mapping_vector": [
        0,
        6,
        5,
        4,
        3,
        1,
        2
      ],
      "total_simulated_shots": 0
    },
    {
      "dataset_id": "r169_non_tie",
      "elapsed_ns": 14517,
      "exact_expected_mapping_vector": [
        0,
        6,
        5,
        4,
        3,
        1,
        2
      ],
      "expected_mapping_vector": [
        0,
        6,
        5,
        4,
        3,
        1,
        2
      ],
      "kind": "standard",
      "mapping_vector": [
        0,
        6,
        5,
        4,
        3,
        1,
        2
      ],
      "matches_expected": true,
      "policy": "source_f64",
      "profile_id": "descending_sorted_order",
      "replay_index": 15,
      "row_hash": "e59a3c189551c6959ee8e87bd140996009905966651237253d7f47ed2746b3a8",
      "simulation_execution_count": 0,
      "source_expected_mapping_vector": [
        0,
        6,
        5,
        4,
        3,
        1,
        2
      ],
      "total_simulated_shots": 0
    },
    {
      "dataset_id": "r169_non_tie",
      "elapsed_ns": 14046,
      "exact_expected_mapping_vector": [
        0,
        6,
        5,
        4,
        3,
        1,
        2
      ],
      "expected_mapping_vector": [
        0,
        6,
        5,
        4,
        3,
        1,
        2
      ],
      "kind": "standard",
      "mapping_vector": [
        0,
        6,
        5,
        4,
        3,
        1,
        2
      ],
      "matches_expected": true,
      "policy": "source_f64",
      "profile_id": "descending_sorted_order",
      "replay_index": 16,
      "row_hash": "f9b165e1a7381188adffd860790a3271d6b7bfa388b3def4fd3642cea3f07a40",
      "simulation_execution_count": 0,
      "source_expected_mapping_vector": [
        0,
        6,
        5,
        4,
        3,
        1,
        2
      ],
      "total_simulated_shots": 0
    },
    {
      "dataset_id": "r169_non_tie",
      "elapsed_ns": 14117,
      "exact_expected_mapping_vector": [
        0,
        6,
        5,
        4,
        3,
        1,
        2
      ],
      "expected_mapping_vector": [
        0,
        6,
        5,
        4,
        3,
        1,
        2
      ],
      "kind": "standard",
      "mapping_vector": [
        0,
        6,
        5,
        4,
        3,
        1,
        2
      ],
      "matches_expected": true,
      "policy": "source_f64",
      "profile_id": "descending_sorted_order",
      "replay_index": 17,
      "row_hash": "228e35fcad0a5a2aaf5519db8576f6999e55c800f4d8cf5cf6814f6a9d31d8c6",
      "simulation_execution_count": 0,
      "source_expected_mapping_vector": [
        0,
        6,
        5,
        4,
        3,
        1,
        2
      ],
      "total_simulated_shots": 0
    },
    {
      "dataset_id": "r169_non_tie",
      "elapsed_ns": 13996,
      "exact_expected_mapping_vector": [
        0,
        6,
        5,
        4,
        3,
        1,
        2
      ],
      "expected_mapping_vector": [
        0,
        6,
        5,
        4,
        3,
        1,
        2
      ],
      "kind": "standard",
      "mapping_vector": [
        0,
        6,
        5,
        4,
        3,
        1,
        2
      ],
      "matches_expected": true,
      "policy": "source_f64",
      "profile_id": "descending_sorted_order",
      "replay_index": 18,
      "row_hash": "a66390f9ba12151e79cd1771d8deed7146ca289e9f1f607f6709a8f2e0cb6cde",
      "simulation_execution_count": 0,
      "source_expected_mapping_vector": [
        0,
        6,
        5,
        4,
        3,
        1,
        2
      ],
      "total_simulated_shots": 0
    },
    {
      "dataset_id": "r169_non_tie",
      "elapsed_ns": 14337,
      "exact_expected_mapping_vector": [
        0,
        6,
        5,
        4,
        3,
        1,
        2
      ],
      "expected_mapping_vector": [
        0,
        6,
        5,
        4,
        3,
        1,
        2
      ],
      "kind": "standard",
      "mapping_vector": [
        0,
        6,
        5,
        4,
        3,
        1,
        2
      ],
      "matches_expected": true,
      "policy": "source_f64",
      "profile_id": "descending_sorted_order",
      "replay_index": 19,
      "row_hash": "c1287e6776a4fe1ca54dedb2f47c8e7a8bbb97c7fce32fee5ee326ca687e39f9",
      "simulation_execution_count": 0,
      "source_expected_mapping_vector": [
        0,
        6,
        5,
        4,
        3,
        1,
        2
      ],
      "total_simulated_shots": 0
    },
    {
      "dataset_id": "r169_non_tie",
      "elapsed_ns": 13905,
      "exact_expected_mapping_vector": [
        0,
        6,
        5,
        4,
        3,
        1,
        2
      ],
      "expected_mapping_vector": [
        0,
        6,
        5,
        4,
        3,
        1,
        2
      ],
      "kind": "standard",
      "mapping_vector": [
        0,
        6,
        5,
        4,
        3,
        1,
        2
      ],
      "matches_expected": true,
      "policy": "source_f64",
      "profile_id": "descending_sorted_order",
      "replay_index": 20,
      "row_hash": "e5765f2639695681bd22e09f124eb012ad19c870cfab523eb80a5ccdbde4e123",
      "simulation_execution_count": 0,
      "source_expected_mapping_vector": [
        0,
        6,
        5,
        4,
        3,
        1,
        2
      ],
      "total_simulated_shots": 0
    },
    {
      "dataset_id": "r169_non_tie",
      "elapsed_ns": 14076,
      "exact_expected_mapping_vector": [
        0,
        6,
        5,
        4,
        3,
        1,
        2
      ],
      "expected_mapping_vector": [
        0,
        6,
        5,
        4,
        3,
        1,
        2
      ],
      "kind": "standard",
      "mapping_vector": [
        0,
        6,
        5,
        4,
        3,
        1,
        2
      ],
      "matches_expected": true,
      "policy": "source_f64",
      "profile_id": "descending_sorted_order",
      "replay_index": 21,
      "row_hash": "ac5f8c13503b34b268b8eb8efa637268d8ee58a054c4b4fdebe27c21cab1b2d2",
      "simulation_execution_count": 0,
      "source_expected_mapping_vector": [
        0,
        6,
        5,
        4,
        3,
        1,
        2
      ],
      "total_simulated_shots": 0
    },
    {
      "dataset_id": "r169_non_tie",
      "elapsed_ns": 14057,
      "exact_expected_mapping_vector": [
        0,
        6,
        5,
        4,
        3,
        1,
        2
      ],
      "expected_mapping_vector": [
        0,
        6,
        5,
        4,
        3,
        1,
        2
      ],
      "kind": "standard",
      "mapping_vector": [
        0,
        6,
        5,
        4,
        3,
        1,
        2
      ],
      "matches_expected": true,
      "policy": "source_f64",
      "profile_id": "descending_sorted_order",
      "replay_index": 22,
      "row_hash": "9809d64b1f8f9839a66fbafe44d4c2d428fe69db08865351f9f4a68aa28c17e5",
      "simulation_execution_count": 0,
      "source_expected_mapping_vector": [
        0,
        6,
        5,
        4,
        3,
        1,
        2
      ],
      "total_simulated_shots": 0
    },
    {
      "dataset_id": "r169_non_tie",
      "elapsed_ns": 14066,
      "exact_expected_mapping_vector": [
        0,
        6,
        5,
        4,
        3,
        1,
        2
      ],
      "expected_mapping_vector": [
        0,
        6,
        5,
        4,
        3,
        1,
        2
      ],
      "kind": "standard",
      "mapping_vector": [
        0,
        6,
        5,
        4,
        3,
        1,
        2
      ],
      "matches_expected": true,
      "policy": "source_f64",
      "profile_id": "descending_sorted_order",
      "replay_index": 23,
      "row_hash": "cbd4d2d716d52cae3fa2d195fcc28b228a1784c5fea633cf9f1aea1b85d30093",
      "simulation_execution_count": 0,
      "source_expected_mapping_vector": [
        0,
        6,
        5,
        4,
        3,
        1,
        2
      ],
      "total_simulated_shots": 0
    },
    {
      "dataset_id": "r169_non_tie",
      "elapsed_ns": 13956,
      "exact_expected_mapping_vector": [
        0,
        6,
        5,
        4,
        3,
        1,
        2
      ],
      "expected_mapping_vector": [
        0,
        6,
        5,
        4,
        3,
        1,
        2
      ],
      "kind": "standard",
      "mapping_vector": [
        0,
        6,
        5,
        4,
        3,
        1,
        2
      ],
      "matches_expected": true,
      "policy": "source_f64",
      "profile_id": "descending_sorted_order",
      "replay_index": 24,
      "row_hash": "c196186bd6787ceec5081cd11dbc225dd53493afc54de81be1388adafdea3047",
      "simulation_execution_count": 0,
      "source_expected_mapping_vector": [
        0,
        6,
        5,
        4,
        3,
        1,
        2
      ],
      "total_simulated_shots": 0
    },
    {
      "dataset_id": "r169_non_tie",
      "elapsed_ns": 14167,
      "exact_expected_mapping_vector": [
        0,
        6,
        5,
        4,
        3,
        1,
        2
      ],
      "expected_mapping_vector": [
        0,
        6,
        5,
        4,
        3,
        1,
        2
      ],
      "kind": "standard",
      "mapping_vector": [
        0,
        6,
        5,
        4,
        3,
        1,
        2
      ],
      "matches_expected": true,
      "policy": "source_f64",
      "profile_id": "descending_sorted_order",
      "replay_index": 25,
      "row_hash": "7a4ea2b6f29a1c89c02c794f34ba588f24c993fac3cd9b5b127a1313c83e5bd0",
      "simulation_execution_count": 0,
      "source_expected_mapping_vector": [
        0,
        6,
        5,
        4,
        3,
        1,
        2
      ],
      "total_simulated_shots": 0
    },
    {
      "dataset_id": "r169_non_tie",
      "elapsed_ns": 13926,
      "exact_expected_mapping_vector": [
        0,
        6,
        5,
        4,
        3,
        1,
        2
      ],
      "expected_mapping_vector": [
        0,
        6,
        5,
        4,
        3,
        1,
        2
      ],
      "kind": "standard",
      "mapping_vector": [
        0,
        6,
        5,
        4,
        3,
        1,
        2
      ],
      "matches_expected": true,
      "policy": "source_f64",
      "profile_id": "descending_sorted_order",
      "replay_index": 26,
      "row_hash": "5e2b66ade59ad5c7019fd62f7dab2065bed1626bdee56898154254438bc2c79a",
      "simulation_execution_count": 0,
      "source_expected_mapping_vector": [
        0,
        6,
        5,
        4,
        3,
        1,
        2
      ],
      "total_simulated_shots": 0
    },
    {
      "dataset_id": "r169_non_tie",
      "elapsed_ns": 13776,
      "exact_expected_mapping_vector": [
        0,
        6,
        5,
        4,
        3,
        1,
        2
      ],
      "expected_mapping_vector": [
        0,
        6,
        5,
        4,
        3,
        1,
        2
      ],
      "kind": "standard",
      "mapping_vector": [
        0,
        6,
        5,
        4,
        3,
        1,
        2
      ],
      "matches_expected": true,
      "policy": "source_f64",
      "profile_id": "descending_sorted_order",
      "replay_index": 27,
      "row_hash": "fcf444e3b27d4299c63099528e9c308ef2b19f010dc382de947c66e1a563463c",
      "simulation_execution_count": 0,
      "source_expected_mapping_vector": [
        0,
        6,
        5,
        4,
        3,
        1,
        2
      ],
      "total_simulated_shots": 0
    },
    {
      "dataset_id": "r169_non_tie",
      "elapsed_ns": 14016,
      "exact_expected_mapping_vector": [
        0,
        6,
        5,
        4,
        3,
        1,
        2
      ],
      "expected_mapping_vector": [
        0,
        6,
        5,
        4,
        3,
        1,
        2
      ],
      "kind": "standard",
      "mapping_vector": [
        0,
        6,
        5,
        4,
        3,
        1,
        2
      ],
      "matches_expected": true,
      "policy": "source_f64",
      "profile_id": "descending_sorted_order",
      "replay_index": 28,
      "row_hash": "276f6f227bf26b9de458719e8acafa4ae15bd439738188bbf9a81d59466b412c",
      "simulation_execution_count": 0,
      "source_expected_mapping_vector": [
        0,
        6,
        5,
        4,
        3,
        1,
        2
      ],
      "total_simulated_shots": 0
    },
    {
      "dataset_id": "r169_non_tie",
      "elapsed_ns": 13976,
      "exact_expected_mapping_vector": [
        0,
        6,
        5,
        4,
        3,
        1,
        2
      ],
      "expected_mapping_vector": [
        0,
        6,
        5,
        4,
        3,
        1,
        2
      ],
      "kind": "standard",
      "mapping_vector": [
        0,
        6,
        5,
        4,
        3,
        1,
        2
      ],
      "matches_expected": true,
      "policy": "source_f64",
      "profile_id": "descending_sorted_order",
      "replay_index": 29,
      "row_hash": "282eb765e274a878f74522722ab0028342c64609057a3b55063b9b3e4dde8e36",
      "simulation_execution_count": 0,
      "source_expected_mapping_vector": [
        0,
        6,
        5,
        4,
        3,
        1,
        2
      ],
      "total_simulated_shots": 0
    },
    {
      "dataset_id": "r169_non_tie",
      "elapsed_ns": 13836,
      "exact_expected_mapping_vector": [
        0,
        6,
        5,
        4,
        3,
        1,
        2
      ],
      "expected_mapping_vector": [
        0,
        6,
        5,
        4,
        3,
        1,
        2
      ],
      "kind": "standard",
      "mapping_vector": [
        0,
        6,
        5,
        4,
        3,
        1,
        2
      ],
      "matches_expected": true,
      "policy": "source_f64",
      "profile_id": "descending_sorted_order",
      "replay_index": 30,
      "row_hash": "4a9544f60a21d55ac8be0f86c2b853a902df7a0696df39a57f9ccceca252bca0",
      "simulation_execution_count": 0,
      "source_expected_mapping_vector": [
        0,
        6,
        5,
        4,
        3,
        1,
        2
      ],
      "total_simulated_shots": 0
    },
    {
      "dataset_id": "r169_non_tie",
      "elapsed_ns": 14026,
      "exact_expected_mapping_vector": [
        0,
        6,
        5,
        4,
        3,
        1,
        2
      ],
      "expected_mapping_vector": [
        0,
        6,
        5,
        4,
        3,
        1,
        2
      ],
      "kind": "standard",
      "mapping_vector": [
        0,
        6,
        5,
        4,
        3,
        1,
        2
      ],
      "matches_expected": true,
      "policy": "source_f64",
      "profile_id": "descending_sorted_order",
      "replay_index": 31,
      "row_hash": "47cc88da902a882d2c6ce592c390b224743175a339d934b763afe82d702013ed",
      "simulation_execution_count": 0,
      "source_expected_mapping_vector": [
        0,
        6,
        5,
        4,
        3,
        1,
        2
      ],
      "total_simulated_shots": 0
    },
    {
      "dataset_id": "r169_non_tie",
      "elapsed_ns": 13916,
      "exact_expected_mapping_vector": [
        0,
        6,
        5,
        4,
        3,
        1,
        2
      ],
      "expected_mapping_vector": [
        0,
        6,
        5,
        4,
        3,
        1,
        2
      ],
      "kind": "standard",
      "mapping_vector": [
        0,
        6,
        5,
        4,
        3,
        1,
        2
      ],
      "matches_expected": true,
      "policy": "source_f64",
      "profile_id": "descending_sorted_order",
      "replay_index": 32,
      "row_hash": "bb51e3782f8c622a14ad04c376483d5c5c411d7ceda2d99639a3f7a002ea6461",
      "simulation_execution_count": 0,
      "source_expected_mapping_vector": [
        0,
        6,
        5,
        4,
        3,
        1,
        2
      ],
      "total_simulated_shots": 0
    },
    {
      "dataset_id": "r169_non_tie",
      "elapsed_ns": 13836,
      "exact_expected_mapping_vector": [
        0,
        6,
        5,
        4,
        3,
        1,
        2
      ],
      "expected_mapping_vector": [
        0,
        6,
        5,
        4,
        3,
        1,
        2
      ],
      "kind": "standard",
      "mapping_vector": [
        0,
        6,
        5,
        4,
        3,
        1,
        2
      ],
      "matches_expected": true,
      "policy": "source_f64",
      "profile_id": "descending_sorted_order",
      "replay_index": 33,
      "row_hash": "9c3447ced8167cb3a7347e1ab8cbc40baeaf34177e0b25bdaaeb878ce48ef7fe",
      "simulation_execution_count": 0,
      "source_expected_mapping_vector": [
        0,
        6,
        5,
        4,
        3,
        1,
        2
      ],
      "total_simulated_shots": 0
    },
    {
      "dataset_id": "r169_non_tie",
      "elapsed_ns": 14056,
      "exact_expected_mapping_vector": [
        0,
        6,
        5,
        4,
        3,
        1,
        2
      ],
      "expected_mapping_vector": [
        0,
        6,
        5,
        4,
        3,
        1,
        2
      ],
      "kind": "standard",
      "mapping_vector": [
        0,
        6,
        5,
        4,
        3,
        1,
        2
      ],
      "matches_expected": true,
      "policy": "source_f64",
      "profile_id": "descending_sorted_order",
      "replay_index": 34,
      "row_hash": "daa82dcdb3d4a300e7a59fdcfbe2dd9048426119a8e7b8821292bbf25b676797",
      "simulation_execution_count": 0,
      "source_expected_mapping_vector": [
        0,
        6,
        5,
        4,
        3,
        1,
        2
      ],
      "total_simulated_shots": 0
    },
    {
      "dataset_id": "r169_non_tie",
      "elapsed_ns": 18765,
      "exact_expected_mapping_vector": [
        0,
        6,
        5,
        4,
        3,
        1,
        2
      ],
      "expected_mapping_vector": [
        0,
        6,
        5,
        4,
        3,
        1,
        2
      ],
      "kind": "standard",
      "mapping_vector": [
        0,
        6,
        5,
        4,
        3,
        1,
        2
      ],
      "matches_expected": true,
      "policy": "source_f64",
      "profile_id": "descending_sorted_order",
      "replay_index": 35,
      "row_hash": "6d98cc3c6a901b686886c444f6252da0bb0f8583bae006ec9b24b34ea17e6371",
      "simulation_execution_count": 0,
      "source_expected_mapping_vector": [
        0,
        6,
        5,
        4,
        3,
        1,
        2
      ],
      "total_simulated_shots": 0
    },
    {
      "dataset_id": "r169_non_tie",
      "elapsed_ns": 15279,
      "exact_expected_mapping_vector": [
        0,
        6,
        5,
        4,
        3,
        1,
        2
      ],
      "expected_mapping_vector": [
        0,
        6,
        5,
        4,
        3,
        1,
        2
      ],
      "kind": "standard",
      "mapping_vector": [
        0,
        6,
        5,
        4,
        3,
        1,
        2
      ],
      "matches_expected": true,
      "policy": "source_f64",
      "profile_id": "descending_sorted_order",
      "replay_index": 36,
      "row_hash": "a752551622dcdb383e2a6e1a4a1abce470a916f7c82910f6a00eec720459c7bc",
      "simulation_execution_count": 0,
      "source_expected_mapping_vector": [
        0,
        6,
        5,
        4,
        3,
        1,
        2
      ],
      "total_simulated_shots": 0
    },
    {
      "dataset_id": "r169_non_tie",
      "elapsed_ns": 14397,
      "exact_expected_mapping_vector": [
        0,
        6,
        5,
        4,
        3,
        1,
        2
      ],
      "expected_mapping_vector": [
        0,
        6,
        5,
        4,
        3,
        1,
        2
      ],
      "kind": "standard",
      "mapping_vector": [
        0,
        6,
        5,
        4,
        3,
        1,
        2
      ],
      "matches_expected": true,
      "policy": "source_f64",
      "profile_id": "descending_sorted_order",
      "replay_index": 37,
      "row_hash": "922ca84cd2513f4f6cde1bb58e412e7394ea32f75133bae0a28896c240ced673",
      "simulation_execution_count": 0,
      "source_expected_mapping_vector": [
        0,
        6,
        5,
        4,
        3,
        1,
        2
      ],
      "total_simulated_shots": 0
    },
    {
      "dataset_id": "r169_non_tie",
      "elapsed_ns": 14096,
      "exact_expected_mapping_vector": [
        0,
        6,
        5,
        4,
        3,
        1,
        2
      ],
      "expected_mapping_vector": [
        0,
        6,
        5,
        4,
        3,
        1,
        2
      ],
      "kind": "standard",
      "mapping_vector": [
        0,
        6,
        5,
        4,
        3,
        1,
        2
      ],
      "matches_expected": true,
      "policy": "source_f64",
      "profile_id": "descending_sorted_order",
      "replay_index": 38,
      "row_hash": "bddd4a9469e894112a66972f06735d65c6052838ba540eb800e027ba9eb160a0",
      "simulation_execution_count": 0,
      "source_expected_mapping_vector": [
        0,
        6,
        5,
        4,
        3,
        1,
        2
      ],
      "total_simulated_shots": 0
    },
    {
      "dataset_id": "r169_non_tie",
      "elapsed_ns": 14136,
      "exact_expected_mapping_vector": [
        0,
        6,
        5,
        4,
        3,
        1,
        2
      ],
      "expected_mapping_vector": [
        0,
        6,
        5,
        4,
        3,
        1,
        2
      ],
      "kind": "standard",
      "mapping_vector": [
        0,
        6,
        5,
        4,
        3,
        1,
        2
      ],
      "matches_expected": true,
      "policy": "source_f64",
      "profile_id": "descending_sorted_order",
      "replay_index": 39,
      "row_hash": "f618c294d7953507c8b32cf6ad5f25b52f63eb76941a4a39a38c47078a29addd",
      "simulation_execution_count": 0,
      "source_expected_mapping_vector": [
        0,
        6,
        5,
        4,
        3,
        1,
        2
      ],
      "total_simulated_shots": 0
    },
    {
      "dataset_id": "r169_non_tie",
      "elapsed_ns": 14186,
      "exact_expected_mapping_vector": [
        0,
        6,
        5,
        4,
        3,
        1,
        2
      ],
      "expected_mapping_vector": [
        0,
        6,
        5,
        4,
        3,
        1,
        2
      ],
      "kind": "standard",
      "mapping_vector": [
        0,
        6,
        5,
        4,
        3,
        1,
        2
      ],
      "matches_expected": true,
      "policy": "source_f64",
      "profile_id": "descending_sorted_order",
      "replay_index": 40,
      "row_hash": "76ab4b46d2f06102c2c6a923155711189e19b9fcecc16e0fec0c2eca5cedcad0",
      "simulation_execution_count": 0,
      "source_expected_mapping_vector": [
        0,
        6,
        5,
        4,
        3,
        1,
        2
      ],
      "total_simulated_shots": 0
    },
    {
      "dataset_id": "r169_non_tie",
      "elapsed_ns": 14497,
      "exact_expected_mapping_vector": [
        0,
        6,
        5,
        4,
        3,
        1,
        2
      ],
      "expected_mapping_vector": [
        0,
        6,
        5,
        4,
        3,
        1,
        2
      ],
      "kind": "standard",
      "mapping_vector": [
        0,
        6,
        5,
        4,
        3,
        1,
        2
      ],
      "matches_expected": true,
      "policy": "source_f64",
      "profile_id": "descending_sorted_order",
      "replay_index": 41,
      "row_hash": "53d4489c0911599fe8f8a2090dbe422ab2b5593f25e7cfbc70d785665385e062",
      "simulation_execution_count": 0,
      "source_expected_mapping_vector": [
        0,
        6,
        5,
        4,
        3,
        1,
        2
      ],
      "total_simulated_shots": 0
    },
    {
      "dataset_id": "r169_non_tie",
      "elapsed_ns": 14317,
      "exact_expected_mapping_vector": [
        0,
        6,
        5,
        4,
        3,
        1,
        2
      ],
      "expected_mapping_vector": [
        0,
        6,
        5,
        4,
        3,
        1,
        2
      ],
      "kind": "standard",
      "mapping_vector": [
        0,
        6,
        5,
        4,
        3,
        1,
        2
      ],
      "matches_expected": true,
      "policy": "source_f64",
      "profile_id": "descending_sorted_order",
      "replay_index": 42,
      "row_hash": "4413720cc13e486d244dd5c43686d3b1624d377f909f3f730129b4ca45be4c05",
      "simulation_execution_count": 0,
      "source_expected_mapping_vector": [
        0,
        6,
        5,
        4,
        3,
        1,
        2
      ],
      "total_simulated_shots": 0
    },
    {
      "dataset_id": "r169_non_tie",
      "elapsed_ns": 13935,
      "exact_expected_mapping_vector": [
        0,
        6,
        5,
        4,
        3,
        1,
        2
      ],
      "expected_mapping_vector": [
        0,
        6,
        5,
        4,
        3,
        1,
        2
      ],
      "kind": "standard",
      "mapping_vector": [
        0,
        6,
        5,
        4,
        3,
        1,
        2
      ],
      "matches_expected": true,
      "policy": "source_f64",
      "profile_id": "descending_sorted_order",
      "replay_index": 43,
      "row_hash": "99bccf1bcca61fff3cdc2582d5655da3366f2e5baf493bd710bc6ad88975b4fe",
      "simulation_execution_count": 0,
      "source_expected_mapping_vector": [
        0,
        6,
        5,
        4,
        3,
        1,
        2
      ],
      "total_simulated_shots": 0
    },
    {
      "dataset_id": "r169_non_tie",
      "elapsed_ns": 14067,
      "exact_expected_mapping_vector": [
        0,
        6,
        5,
        4,
        3,
        1,
        2
      ],
      "expected_mapping_vector": [
        0,
        6,
        5,
        4,
        3,
        1,
        2
      ],
      "kind": "standard",
      "mapping_vector": [
        0,
        6,
        5,
        4,
        3,
        1,
        2
      ],
      "matches_expected": true,
      "policy": "source_f64",
      "profile_id": "descending_sorted_order",
      "replay_index": 44,
      "row_hash": "50cdb025d22ae297bf1cb0ce7292034b8d9af60d10d17cd5b07ec7f8fa92eb2a",
      "simulation_execution_count": 0,
      "source_expected_mapping_vector": [
        0,
        6,
        5,
        4,
        3,
        1,
        2
      ],
      "total_simulated_shots": 0
    },
    {
      "dataset_id": "r169_non_tie",
      "elapsed_ns": 14136,
      "exact_expected_mapping_vector": [
        0,
        6,
        5,
        4,
        3,
        1,
        2
      ],
      "expected_mapping_vector": [
        0,
        6,
        5,
        4,
        3,
        1,
        2
      ],
      "kind": "standard",
      "mapping_vector": [
        0,
        6,
        5,
        4,
        3,
        1,
        2
      ],
      "matches_expected": true,
      "policy": "source_f64",
      "profile_id": "descending_sorted_order",
      "replay_index": 45,
      "row_hash": "4145571f26a60150c59ed0356cc708d6bab1356af070ce65a38d9fec89da47e0",
      "simulation_execution_count": 0,
      "source_expected_mapping_vector": [
        0,
        6,
        5,
        4,
        3,
        1,
        2
      ],
      "total_simulated_shots": 0
    },
    {
      "dataset_id": "r169_non_tie",
      "elapsed_ns": 14076,
      "exact_expected_mapping_vector": [
        0,
        6,
        5,
        4,
        3,
        1,
        2
      ],
      "expected_mapping_vector": [
        0,
        6,
        5,
        4,
        3,
        1,
        2
      ],
      "kind": "standard",
      "mapping_vector": [
        0,
        6,
        5,
        4,
        3,
        1,
        2
      ],
      "matches_expected": true,
      "policy": "source_f64",
      "profile_id": "descending_sorted_order",
      "replay_index": 46,
      "row_hash": "1cad972aa59d168d21acbdc4e9a7055a5e04fbf75a94d272ee54fc14430de1dc",
      "simulation_execution_count": 0,
      "source_expected_mapping_vector": [
        0,
        6,
        5,
        4,
        3,
        1,
        2
      ],
      "total_simulated_shots": 0
    },
    {
      "dataset_id": "r169_non_tie",
      "elapsed_ns": 18805,
      "exact_expected_mapping_vector": [
        0,
        6,
        5,
        4,
        3,
        1,
        2
      ],
      "expected_mapping_vector": [
        0,
        6,
        5,
        4,
        3,
        1,
        2
      ],
      "kind": "standard",
      "mapping_vector": [
        0,
        6,
        5,
        4,
        3,
        1,
        2
      ],
      "matches_expected": true,
      "policy": "source_f64",
      "profile_id": "descending_sorted_order",
      "replay_index": 47,
      "row_hash": "c80ae9b57ebc469a7d7e3ad1b89aa0babe59bb66e9c051e4ccb14d52ca527387",
      "simulation_execution_count": 0,
      "source_expected_mapping_vector": [
        0,
        6,
        5,
        4,
        3,
        1,
        2
      ],
      "total_simulated_shots": 0
    },
    {
      "dataset_id": "r169_non_tie",
      "elapsed_ns": 14698,
      "exact_expected_mapping_vector": [
        0,
        6,
        5,
        4,
        3,
        1,
        2
      ],
      "expected_mapping_vector": [
        0,
        6,
        5,
        4,
        3,
        1,
        2
      ],
      "kind": "standard",
      "mapping_vector": [
        0,
        6,
        5,
        4,
        3,
        1,
        2
      ],
      "matches_expected": true,
      "policy": "source_f64",
      "profile_id": "descending_sorted_order",
      "replay_index": 48,
      "row_hash": "43dedcf7d7492f660e51af13eeb81fc5aaaebe137956134d901aaaf9990336a7",
      "simulation_execution_count": 0,
      "source_expected_mapping_vector": [
        0,
        6,
        5,
        4,
        3,
        1,
        2
      ],
      "total_simulated_shots": 0
    },
    {
      "dataset_id": "r169_non_tie",
      "elapsed_ns": 14187,
      "exact_expected_mapping_vector": [
        0,
        6,
        5,
        4,
        3,
        1,
        2
      ],
      "expected_mapping_vector": [
        0,
        6,
        5,
        4,
        3,
        1,
        2
      ],
      "kind": "standard",
      "mapping_vector": [
        0,
        6,
        5,
        4,
        3,
        1,
        2
      ],
      "matches_expected": true,
      "policy": "source_f64",
      "profile_id": "descending_sorted_order",
      "replay_index": 49,
      "row_hash": "a19a4560d29be3a77b7a714ae18b0c19ec1b86f4b0792ceaa4297c401979b402",
      "simulation_execution_count": 0,
      "source_expected_mapping_vector": [
        0,
        6,
        5,
        4,
        3,
        1,
        2
      ],
      "total_simulated_shots": 0
    },
    {
      "dataset_id": "r169_non_tie",
      "elapsed_ns": 13956,
      "exact_expected_mapping_vector": [
        0,
        6,
        5,
        4,
        3,
        1,
        2
      ],
      "expected_mapping_vector": [
        0,
        6,
        5,
        4,
        3,
        1,
        2
      ],
      "kind": "standard",
      "mapping_vector": [
        0,
        6,
        5,
        4,
        3,
        1,
        2
      ],
      "matches_expected": true,
      "policy": "source_f64",
      "profile_id": "descending_sorted_order",
      "replay_index": 50,
      "row_hash": "84aa2749976d2de80bca6a01085157f7180744ebf073923de07277037b42232c",
      "simulation_execution_count": 0,
      "source_expected_mapping_vector": [
        0,
        6,
        5,
        4,
        3,
        1,
        2
      ],
      "total_simulated_shots": 0
    },
    {
      "dataset_id": "r169_non_tie",
      "elapsed_ns": 13916,
      "exact_expected_mapping_vector": [
        0,
        6,
        5,
        4,
        3,
        1,
        2
      ],
      "expected_mapping_vector": [
        0,
        6,
        5,
        4,
        3,
        1,
        2
      ],
      "kind": "standard",
      "mapping_vector": [
        0,
        6,
        5,
        4,
        3,
        1,
        2
      ],
      "matches_expected": true,
      "policy": "source_f64",
      "profile_id": "descending_sorted_order",
      "replay_index": 51,
      "row_hash": "44c26761829622d53fd7b055691101b05d3c2d48f3a41cd86bfdab97f3981607",
      "simulation_execution_count": 0,
      "source_expected_mapping_vector": [
        0,
        6,
        5,
        4,
        3,
        1,
        2
      ],
      "total_simulated_shots": 0
    },
    {
      "dataset_id": "r169_non_tie",
      "elapsed_ns": 14757,
      "exact_expected_mapping_vector": [
        0,
        6,
        5,
        4,
        3,
        1,
        2
      ],
      "expected_mapping_vector": [
        0,
        6,
        5,
        4,
        3,
        1,
        2
      ],
      "kind": "standard",
      "mapping_vector": [
        0,
        6,
        5,
        4,
        3,
        1,
        2
      ],
      "matches_expected": true,
      "policy": "source_f64",
      "profile_id": "descending_sorted_order",
      "replay_index": 52,
      "row_hash": "faaf73cb6dd21db0a523fb413f01b6546707246cf50926f237c55b7eb75a2c6f",
      "simulation_execution_count": 0,
      "source_expected_mapping_vector": [
        0,
        6,
        5,
        4,
        3,
        1,
        2
      ],
      "total_simulated_shots": 0
    },
    {
      "dataset_id": "r169_non_tie",
      "elapsed_ns": 13766,
      "exact_expected_mapping_vector": [
        0,
        6,
        5,
        4,
        3,
        1,
        2
      ],
      "expected_mapping_vector": [
        0,
        6,
        5,
        4,
        3,
        1,
        2
      ],
      "kind": "standard",
      "mapping_vector": [
        0,
        6,
        5,
        4,
        3,
        1,
        2
      ],
      "matches_expected": true,
      "policy": "source_f64",
      "profile_id": "descending_sorted_order",
      "replay_index": 53,
      "row_hash": "bc2cc23633566d5e7b341d691892f28d30c77d9640243269b728a426d209351d",
      "simulation_execution_count": 0,
      "source_expected_mapping_vector": [
        0,
        6,
        5,
        4,
        3,
        1,
        2
      ],
      "total_simulated_shots": 0
    },
    {
      "dataset_id": "r169_non_tie",
      "elapsed_ns": 13936,
      "exact_expected_mapping_vector": [
        0,
        6,
        5,
        4,
        3,
        1,
        2
      ],
      "expected_mapping_vector": [
        0,
        6,
        5,
        4,
        3,
        1,
        2
      ],
      "kind": "standard",
      "mapping_vector": [
        0,
        6,
        5,
        4,
        3,
        1,
        2
      ],
      "matches_expected": true,
      "policy": "source_f64",
      "profile_id": "descending_sorted_order",
      "replay_index": 54,
      "row_hash": "37d2a123324b0df08a871d26530d77d7f34e19c6244b42de88be141a692e4fe4",
      "simulation_execution_count": 0,
      "source_expected_mapping_vector": [
        0,
        6,
        5,
        4,
        3,
        1,
        2
      ],
      "total_simulated_shots": 0
    },
    {
      "dataset_id": "r169_non_tie",
      "elapsed_ns": 14326,
      "exact_expected_mapping_vector": [
        0,
        6,
        5,
        4,
        3,
        1,
        2
      ],
      "expected_mapping_vector": [
        0,
        6,
        5,
        4,
        3,
        1,
        2
      ],
      "kind": "standard",
      "mapping_vector": [
        0,
        6,
        5,
        4,
        3,
        1,
        2
      ],
      "matches_expected": true,
      "policy": "source_f64",
      "profile_id": "descending_sorted_order",
      "replay_index": 55,
      "row_hash": "db93857242de6e1bbf42c4ffe195dfc7690c002b8493027f117d7cd9c47723e3",
      "simulation_execution_count": 0,
      "source_expected_mapping_vector": [
        0,
        6,
        5,
        4,
        3,
        1,
        2
      ],
      "total_simulated_shots": 0
    },
    {
      "dataset_id": "r169_non_tie",
      "elapsed_ns": 13835,
      "exact_expected_mapping_vector": [
        0,
        6,
        5,
        4,
        3,
        1,
        2
      ],
      "expected_mapping_vector": [
        0,
        6,
        5,
        4,
        3,
        1,
        2
      ],
      "kind": "standard",
      "mapping_vector": [
        0,
        6,
        5,
        4,
        3,
        1,
        2
      ],
      "matches_expected": true,
      "policy": "source_f64",
      "profile_id": "descending_sorted_order",
      "replay_index": 56,
      "row_hash": "843b86cbe7fd5db74260763446f249443fd0086112ce3758a141d43d199165bf",
      "simulation_execution_count": 0,
      "source_expected_mapping_vector": [
        0,
        6,
        5,
        4,
        3,
        1,
        2
      ],
      "total_simulated_shots": 0
    },
    {
      "dataset_id": "r169_non_tie",
      "elapsed_ns": 13866,
      "exact_expected_mapping_vector": [
        0,
        6,
        5,
        4,
        3,
        1,
        2
      ],
      "expected_mapping_vector": [
        0,
        6,
        5,
        4,
        3,
        1,
        2
      ],
      "kind": "standard",
      "mapping_vector": [
        0,
        6,
        5,
        4,
        3,
        1,
        2
      ],
      "matches_expected": true,
      "policy": "source_f64",
      "profile_id": "descending_sorted_order",
      "replay_index": 57,
      "row_hash": "bca2f4e80bb6e4b83165780bd9aa7f1d67b42d3e51cc31eb24c2fa3147f273b8",
      "simulation_execution_count": 0,
      "source_expected_mapping_vector": [
        0,
        6,
        5,
        4,
        3,
        1,
        2
      ],
      "total_simulated_shots": 0
    },
    {
      "dataset_id": "r169_non_tie",
      "elapsed_ns": 13897,
      "exact_expected_mapping_vector": [
        0,
        6,
        5,
        4,
        3,
        1,
        2
      ],
      "expected_mapping_vector": [
        0,
        6,
        5,
        4,
        3,
        1,
        2
      ],
      "kind": "standard",
      "mapping_vector": [
        0,
        6,
        5,
        4,
        3,
        1,
        2
      ],
      "matches_expected": true,
      "policy": "source_f64",
      "profile_id": "descending_sorted_order",
      "replay_index": 58,
      "row_hash": "632c8c135c61200305d5fb7e4946248c614b0c6eb55ed9968b3ca9982ec64421",
      "simulation_execution_count": 0,
      "source_expected_mapping_vector": [
        0,
        6,
        5,
        4,
        3,
        1,
        2
      ],
      "total_simulated_shots": 0
    },
    {
      "dataset_id": "r169_non_tie",
      "elapsed_ns": 13755,
      "exact_expected_mapping_vector": [
        0,
        6,
        5,
        4,
        3,
        1,
        2
      ],
      "expected_mapping_vector": [
        0,
        6,
        5,
        4,
        3,
        1,
        2
      ],
      "kind": "standard",
      "mapping_vector": [
        0,
        6,
        5,
        4,
        3,
        1,
        2
      ],
      "matches_expected": true,
      "policy": "source_f64",
      "profile_id": "descending_sorted_order",
      "replay_index": 59,
      "row_hash": "2e693f2f5b1203603d599ae5952c39fcb17a2d3fcae8d96eb73cf901050968f5",
      "simulation_execution_count": 0,
      "source_expected_mapping_vector": [
        0,
        6,
        5,
        4,
        3,
        1,
        2
      ],
      "total_simulated_shots": 0
    },
    {
      "dataset_id": "r169_non_tie",
      "elapsed_ns": 13966,
      "exact_expected_mapping_vector": [
        0,
        6,
        5,
        4,
        3,
        1,
        2
      ],
      "expected_mapping_vector": [
        0,
        6,
        5,
        4,
        3,
        1,
        2
      ],
      "kind": "standard",
      "mapping_vector": [
        0,
        6,
        5,
        4,
        3,
        1,
        2
      ],
      "matches_expected": true,
      "policy": "source_f64",
      "profile_id": "descending_sorted_order",
      "replay_index": 60,
      "row_hash": "69ea90589fda0e64f53c42641f58c072b5363c882d7e4b1341839ed281efee11",
      "simulation_execution_count": 0,
      "source_expected_mapping_vector": [
        0,
        6,
        5,
        4,
        3,
        1,
        2
      ],
      "total_simulated_shots": 0
    },
    {
      "dataset_id": "r169_non_tie",
      "elapsed_ns": 13785,
      "exact_expected_mapping_vector": [
        0,
        6,
        5,
        4,
        3,
        1,
        2
      ],
      "expected_mapping_vector": [
        0,
        6,
        5,
        4,
        3,
        1,
        2
      ],
      "kind": "standard",
      "mapping_vector": [
        0,
        6,
        5,
        4,
        3,
        1,
        2
      ],
      "matches_expected": true,
      "policy": "source_f64",
      "profile_id": "descending_sorted_order",
      "replay_index": 61,
      "row_hash": "099b539c4457923d418a462bb455e2d4062f3fabd087610152b54192b49e5634",
      "simulation_execution_count": 0,
      "source_expected_mapping_vector": [
        0,
        6,
        5,
        4,
        3,
        1,
        2
      ],
      "total_simulated_shots": 0
    },
    {
      "dataset_id": "r169_non_tie",
      "elapsed_ns": 13796,
      "exact_expected_mapping_vector": [
        0,
        6,
        5,
        4,
        3,
        1,
        2
      ],
      "expected_mapping_vector": [
        0,
        6,
        5,
        4,
        3,
        1,
        2
      ],
      "kind": "standard",
      "mapping_vector": [
        0,
        6,
        5,
        4,
        3,
        1,
        2
      ],
      "matches_expected": true,
      "policy": "source_f64",
      "profile_id": "descending_sorted_order",
      "replay_index": 62,
      "row_hash": "ba52c64612683df80910ce806e3af82147d6a6682cb154e1a2059dd098521cda",
      "simulation_execution_count": 0,
      "source_expected_mapping_vector": [
        0,
        6,
        5,
        4,
        3,
        1,
        2
      ],
      "total_simulated_shots": 0
    },
    {
      "dataset_id": "r169_non_tie",
      "elapsed_ns": 14136,
      "exact_expected_mapping_vector": [
        0,
        6,
        5,
        4,
        3,
        1,
        2
      ],
      "expected_mapping_vector": [
        0,
        6,
        5,
        4,
        3,
        1,
        2
      ],
      "kind": "standard",
      "mapping_vector": [
        0,
        6,
        5,
        4,
        3,
        1,
        2
      ],
      "matches_expected": true,
      "policy": "source_f64",
      "profile_id": "descending_sorted_order",
      "replay_index": 63,
      "row_hash": "c00a47b8f47c30420325701fd6ebec8eb9889a58e4be16d1e7c1dcd6be7cd905",
      "simulation_execution_count": 0,
      "source_expected_mapping_vector": [
        0,
        6,
        5,
        4,
        3,
        1,
        2
      ],
      "total_simulated_shots": 0
    }
  ],
  "simulation_execution_count": 0,
  "source_worker_path": "results/B4_B8_R169_target_compatible_candidate_replay/descending_sorted_order.json",
  "source_worker_sha256": "dff52754d8c4e9dc021cf3ba2fa46bcc4b97516382089b95eeccfb3845806070",
  "started_at_unix": 1784563311,
  "target_descriptor_sha256": "702c8fd9dcf67a069e7af63e31a57c74c17aaa5e3c5b6d8c2e28ec0c049c0de7",
  "total_simulated_shots": 0,
  "warmup_call_count": 16,
  "warmup_matches_expected": 16
}
