{
  "benchmark_id": "B1",
  "claim_boundary": {
    "b7_ledger_improvement_claimed": false,
    "cost_model_accepted": false,
    "next_gate": "Use this as CM-04 logical routing evidence, then build CM-05 factory amortization and CM-06 shared-error budget evidence before any physical theta-sharing cost model can be accepted.",
    "physical_layout_claimed": false,
    "physical_resource_reduction_claimed": false,
    "resource_saving_claimed": false,
    "rewrite_claimed": false,
    "semantic_certificate_claimed": false,
    "semantic_rewrite_verified": false,
    "supported_claim": "Each replay-verified shared-theta object now has an explicit logical anchor and a replayed occurrence-to-anchor route packet under a source-QASM line topology scaffold.",
    "unsupported_claims": [
      "No physical device layout is claimed.",
      "No factory-amortization or error-budget model is supplied.",
      "No occurrence-removing semantic rewrite is verified.",
      "No B7 ledger reduction is counted."
    ]
  },
  "last_updated": "2026-06-18",
  "layout_route_rows": [
    {
      "canonical_theta": 0.420540811611,
      "consumer_qubit_count": 6,
      "factory_amortization_model_present": false,
      "layout_route_complete": true,
      "logical_anchor_qubit": 10,
      "max_logical_hop_count": 9,
      "object_id": "cone01_shared_theta_01",
      "physical_layout_assigned": false,
      "route_packet_count": 16,
      "route_packets": [
        {
          "canonical_theta_matches_object": true,
          "consumer_qubit": 13,
          "line_number": 94,
          "logical_anchor_qubit": 10,
          "logical_hop_count": 3,
          "logical_line_path": [
            10,
            11,
            12,
            13
          ]
        },
        {
          "canonical_theta_matches_object": true,
          "consumer_qubit": 13,
          "line_number": 97,
          "logical_anchor_qubit": 10,
          "logical_hop_count": 3,
          "logical_line_path": [
            10,
            11,
            12,
            13
          ]
        },
        {
          "canonical_theta_matches_object": true,
          "consumer_qubit": 2,
          "line_number": 252,
          "logical_anchor_qubit": 10,
          "logical_hop_count": 8,
          "logical_line_path": [
            10,
            9,
            8,
            7,
            6,
            5,
            4,
            3,
            2
          ]
        },
        {
          "canonical_theta_matches_object": true,
          "consumer_qubit": 2,
          "line_number": 255,
          "logical_anchor_qubit": 10,
          "logical_hop_count": 8,
          "logical_line_path": [
            10,
            9,
            8,
            7,
            6,
            5,
            4,
            3,
            2
          ]
        },
        {
          "canonical_theta_matches_object": true,
          "consumer_qubit": 10,
          "line_number": 345,
          "logical_anchor_qubit": 10,
          "logical_hop_count": 0,
          "logical_line_path": [
            10
          ]
        },
        {
          "canonical_theta_matches_object": true,
          "consumer_qubit": 10,
          "line_number": 348,
          "logical_anchor_qubit": 10,
          "logical_hop_count": 0,
          "logical_line_path": [
            10
          ]
        },
        {
          "canonical_theta_matches_object": true,
          "consumer_qubit": 16,
          "line_number": 427,
          "logical_anchor_qubit": 10,
          "logical_hop_count": 6,
          "logical_line_path": [
            10,
            11,
            12,
            13,
            14,
            15,
            16
          ]
        },
        {
          "canonical_theta_matches_object": true,
          "consumer_qubit": 10,
          "line_number": 1254,
          "logical_anchor_qubit": 10,
          "logical_hop_count": 0,
          "logical_line_path": [
            10
          ]
        },
        {
          "canonical_theta_matches_object": true,
          "consumer_qubit": 10,
          "line_number": 1257,
          "logical_anchor_qubit": 10,
          "logical_hop_count": 0,
          "logical_line_path": [
            10
          ]
        },
        {
          "canonical_theta_matches_object": true,
          "consumer_qubit": 2,
          "line_number": 1310,
          "logical_anchor_qubit": 10,
          "logical_hop_count": 8,
          "logical_line_path": [
            10,
            9,
            8,
            7,
            6,
            5,
            4,
            3,
            2
          ]
        },
        {
          "canonical_theta_matches_object": true,
          "consumer_qubit": 2,
          "line_number": 1313,
          "logical_anchor_qubit": 10,
          "logical_hop_count": 8,
          "logical_line_path": [
            10,
            9,
            8,
            7,
            6,
            5,
            4,
            3,
            2
          ]
        },
        {
          "canonical_theta_matches_object": true,
          "consumer_qubit": 13,
          "line_number": 1366,
          "logical_anchor_qubit": 10,
          "logical_hop_count": 3,
          "logical_line_path": [
            10,
            11,
            12,
            13
          ]
        },
        {
          "canonical_theta_matches_object": true,
          "consumer_qubit": 13,
          "line_number": 1369,
          "logical_anchor_qubit": 10,
          "logical_hop_count": 3,
          "logical_line_path": [
            10,
            11,
            12,
            13
          ]
        },
        {
          "canonical_theta_matches_object": true,
          "consumer_qubit": 1,
          "line_number": 1422,
          "logical_anchor_qubit": 10,
          "logical_hop_count": 9,
          "logical_line_path": [
            10,
            9,
            8,
            7,
            6,
            5,
            4,
            3,
            2,
            1
          ]
        },
        {
          "canonical_theta_matches_object": true,
          "consumer_qubit": 8,
          "line_number": 1543,
          "logical_anchor_qubit": 10,
          "logical_hop_count": 2,
          "logical_line_path": [
            10,
            9,
            8
          ]
        },
        {
          "canonical_theta_matches_object": true,
          "consumer_qubit": 8,
          "line_number": 1546,
          "logical_anchor_qubit": 10,
          "logical_hop_count": 2,
          "logical_line_path": [
            10,
            9,
            8
          ]
        }
      ],
      "total_logical_hop_count": 63
    },
    {
      "canonical_theta": 0.364857351786,
      "consumer_qubit_count": 7,
      "factory_amortization_model_present": false,
      "layout_route_complete": true,
      "logical_anchor_qubit": 10,
      "max_logical_hop_count": 9,
      "object_id": "cone01_shared_theta_02",
      "physical_layout_assigned": false,
      "route_packet_count": 10,
      "route_packets": [
        {
          "canonical_theta_matches_object": true,
          "consumer_qubit": 13,
          "line_number": 29,
          "logical_anchor_qubit": 10,
          "logical_hop_count": 3,
          "logical_line_path": [
            10,
            11,
            12,
            13
          ]
        },
        {
          "canonical_theta_matches_object": true,
          "consumer_qubit": 1,
          "line_number": 87,
          "logical_anchor_qubit": 10,
          "logical_hop_count": 9,
          "logical_line_path": [
            10,
            9,
            8,
            7,
            6,
            5,
            4,
            3,
            2,
            1
          ]
        },
        {
          "canonical_theta_matches_object": true,
          "consumer_qubit": 2,
          "line_number": 187,
          "logical_anchor_qubit": 10,
          "logical_hop_count": 8,
          "logical_line_path": [
            10,
            9,
            8,
            7,
            6,
            5,
            4,
            3,
            2
          ]
        },
        {
          "canonical_theta_matches_object": true,
          "consumer_qubit": 13,
          "line_number": 245,
          "logical_anchor_qubit": 10,
          "logical_hop_count": 3,
          "logical_line_path": [
            10,
            11,
            12,
            13
          ]
        },
        {
          "canonical_theta_matches_object": true,
          "consumer_qubit": 10,
          "line_number": 280,
          "logical_anchor_qubit": 10,
          "logical_hop_count": 0,
          "logical_line_path": [
            10
          ]
        },
        {
          "canonical_theta_matches_object": true,
          "consumer_qubit": 2,
          "line_number": 338,
          "logical_anchor_qubit": 10,
          "logical_hop_count": 8,
          "logical_line_path": [
            10,
            9,
            8,
            7,
            6,
            5,
            4,
            3,
            2
          ]
        },
        {
          "canonical_theta_matches_object": true,
          "consumer_qubit": 16,
          "line_number": 359,
          "logical_anchor_qubit": 10,
          "logical_hop_count": 6,
          "logical_line_path": [
            10,
            11,
            12,
            13,
            14,
            15,
            16
          ]
        },
        {
          "canonical_theta_matches_object": true,
          "consumer_qubit": 10,
          "line_number": 417,
          "logical_anchor_qubit": 10,
          "logical_hop_count": 0,
          "logical_line_path": [
            10
          ]
        },
        {
          "canonical_theta_matches_object": true,
          "consumer_qubit": 8,
          "line_number": 1478,
          "logical_anchor_qubit": 10,
          "logical_hop_count": 2,
          "logical_line_path": [
            10,
            9,
            8
          ]
        },
        {
          "canonical_theta_matches_object": true,
          "consumer_qubit": 12,
          "line_number": 1536,
          "logical_anchor_qubit": 10,
          "logical_hop_count": 2,
          "logical_line_path": [
            10,
            11,
            12
          ]
        }
      ],
      "total_logical_hop_count": 41
    },
    {
      "canonical_theta": 0.99803486463,
      "consumer_qubit_count": 4,
      "factory_amortization_model_present": false,
      "layout_route_complete": true,
      "logical_anchor_qubit": 10,
      "max_logical_hop_count": 8,
      "object_id": "cone01_shared_theta_03",
      "physical_layout_assigned": false,
      "route_packet_count": 6,
      "route_packets": [
        {
          "canonical_theta_matches_object": true,
          "consumer_qubit": 2,
          "line_number": 139,
          "logical_anchor_qubit": 10,
          "logical_hop_count": 8,
          "logical_line_path": [
            10,
            9,
            8,
            7,
            6,
            5,
            4,
            3,
            2
          ]
        },
        {
          "canonical_theta_matches_object": true,
          "consumer_qubit": 10,
          "line_number": 152,
          "logical_anchor_qubit": 10,
          "logical_hop_count": 0,
          "logical_line_path": [
            10
          ]
        },
        {
          "canonical_theta_matches_object": true,
          "consumer_qubit": 10,
          "line_number": 155,
          "logical_anchor_qubit": 10,
          "logical_hop_count": 0,
          "logical_line_path": [
            10
          ]
        },
        {
          "canonical_theta_matches_object": true,
          "consumer_qubit": 4,
          "line_number": 1588,
          "logical_anchor_qubit": 10,
          "logical_hop_count": 6,
          "logical_line_path": [
            10,
            9,
            8,
            7,
            6,
            5,
            4
          ]
        },
        {
          "canonical_theta_matches_object": true,
          "consumer_qubit": 15,
          "line_number": 1599,
          "logical_anchor_qubit": 10,
          "logical_hop_count": 5,
          "logical_line_path": [
            10,
            11,
            12,
            13,
            14,
            15
          ]
        },
        {
          "canonical_theta_matches_object": true,
          "consumer_qubit": 15,
          "line_number": 1602,
          "logical_anchor_qubit": 10,
          "logical_hop_count": 5,
          "logical_line_path": [
            10,
            11,
            12,
            13,
            14,
            15
          ]
        }
      ],
      "total_logical_hop_count": 24
    },
    {
      "canonical_theta": 2.813468447841,
      "consumer_qubit_count": 2,
      "factory_amortization_model_present": false,
      "layout_route_complete": true,
      "logical_anchor_qubit": 5,
      "max_logical_hop_count": 11,
      "object_id": "cone01_shared_theta_04",
      "physical_layout_assigned": false,
      "route_packet_count": 3,
      "route_packets": [
        {
          "canonical_theta_matches_object": true,
          "consumer_qubit": 16,
          "line_number": 462,
          "logical_anchor_qubit": 5,
          "logical_hop_count": 11,
          "logical_line_path": [
            5,
            6,
            7,
            8,
            9,
            10,
            11,
            12,
            13,
            14,
            15,
            16
          ]
        },
        {
          "canonical_theta_matches_object": true,
          "consumer_qubit": 5,
          "line_number": 474,
          "logical_anchor_qubit": 5,
          "logical_hop_count": 0,
          "logical_line_path": [
            5
          ]
        },
        {
          "canonical_theta_matches_object": true,
          "consumer_qubit": 5,
          "line_number": 477,
          "logical_anchor_qubit": 5,
          "logical_hop_count": 0,
          "logical_line_path": [
            5
          ]
        }
      ],
      "total_logical_hop_count": 11
    }
  ],
  "linked_b7_problem_id": 21,
  "method": "b1_b7_cone01_shared_theta_layout_routing_gate_v0",
  "model_status": "logical_layout_routing_scaffold_not_physical_layout",
  "problem_id": 25,
  "source_shared_theta_replay_verifier_gate": "results/B1_B7_cone01_shared_theta_replay_verifier_gate_v0.json",
  "status": "cone01_shared_theta_logical_layout_routing_scaffold",
  "summary": {
    "b7_ledger_improvement_claimed": false,
    "candidate_window_count": 35,
    "cost_model_accepted": false,
    "factory_amortization_model_present": false,
    "layout_routed_object_count": 4,
    "layout_routed_occurrence_count": 35,
    "layout_routing_gate_passed": true,
    "logical_anchor_object_count": 4,
    "logical_line_topology_qubit_count": 16,
    "logical_route_packet_count": 35,
    "max_logical_hop_count": 11,
    "missing_route_count": 0,
    "occurrence_ledger_proxy_t_reduction": 0,
    "occurrence_ledger_removed_occurrences": 0,
    "physical_layout_claimed": false,
    "physical_resource_reduction_claimed": false,
    "replay_verified_object_count": 4,
    "replayed_occurrence_count": 35,
    "resource_saving_claimed": false,
    "rewrite_claimed": false,
    "semantic_certificate_claimed": false,
    "semantic_rewrite_verified": false,
    "shared_error_budget_present": false,
    "shared_synthesis_object_count": 4,
    "total_logical_hop_count": 139,
    "validation_error_count": 0
  },
  "title": "B1/B7 cone_01 shared-theta logical layout/routing scaffold",
  "validation_errors": [],
  "version": "0.1",
  "workload": "qasmbench_medium_exact/gcm_h6.qasm"
}
