{
  "adjusted_survivor_rows": [
    {
      "baseline_distance": 7,
      "baseline_space_time_volume": 826,
      "candidate_distance": 5,
      "candidate_space_time_volume": 386.4,
      "decoder_adjusted_candidate_space_time_volume": 521.64,
      "decoder_adjusted_surviving_d5_d7_improvement": true,
      "decoder_adjusted_volume_reduction": 1.5834675254965112,
      "decoder_risk_multiplier": 1.35,
      "false_positive_rate_per_tick": 0.001,
      "false_positive_ratio": 1.0,
      "leakage_rate_per_tick": 0.005,
      "max_false_positive_rate_per_tick": 0.001,
      "max_missed_leakage_rate_per_tick": 0.001,
      "memory_basis": "x",
      "missed_leakage_rate_per_tick": 0.0009999999999999998,
      "missed_leakage_ratio": 0.9999999999999998,
      "physical_error": 0.005,
      "posterior_leakage_probability_given_flag": 0.8008008008008007,
      "posterior_shortfall_ratio": 0.0,
      "posterior_threshold": 0.75,
      "profile": "field_detector_0p80",
      "raw_surviving_d5_d7_improvement": true,
      "raw_volume_reduction_vs_baseline": 2.13768115942029,
      "risk_budget": "mild_decoder_penalty",
      "shot_conditioned_accept": true,
      "target_logical_error": 0.05
    },
    {
      "baseline_distance": 9,
      "baseline_space_time_volume": 1692,
      "candidate_distance": 7,
      "candidate_space_time_volume": 973.6474999999998,
      "decoder_adjusted_candidate_space_time_volume": 1314.4241249999998,
      "decoder_adjusted_surviving_d5_d7_improvement": true,
      "decoder_adjusted_volume_reduction": 1.2872557402276836,
      "decoder_risk_multiplier": 1.35,
      "false_positive_rate_per_tick": 0.001,
      "false_positive_ratio": 1.0,
      "leakage_rate_per_tick": 0.01,
      "max_false_positive_rate_per_tick": 0.001,
      "max_missed_leakage_rate_per_tick": 0.001,
      "memory_basis": "x",
      "missed_leakage_rate_per_tick": 0.0009999999999999998,
      "missed_leakage_ratio": 0.9999999999999998,
      "physical_error": 0.001,
      "posterior_leakage_probability_given_flag": 0.9009009009009009,
      "posterior_shortfall_ratio": 0.0,
      "posterior_threshold": 0.75,
      "profile": "nominal_lab_detector_0p90",
      "raw_surviving_d5_d7_improvement": true,
      "raw_volume_reduction_vs_baseline": 1.737795249307373,
      "risk_budget": "mild_decoder_penalty",
      "shot_conditioned_accept": true,
      "target_logical_error": 0.02
    },
    {
      "baseline_distance": 9,
      "baseline_space_time_volume": 1692,
      "candidate_distance": 5,
      "candidate_space_time_volume": 377.19999999999993,
      "decoder_adjusted_candidate_space_time_volume": 509.2199999999999,
      "decoder_adjusted_surviving_d5_d7_improvement": true,
      "decoder_adjusted_volume_reduction": 3.322728879462708,
      "decoder_risk_multiplier": 1.35,
      "false_positive_rate_per_tick": 0.001,
      "false_positive_ratio": 1.0,
      "leakage_rate_per_tick": 0.01,
      "max_false_positive_rate_per_tick": 0.001,
      "max_missed_leakage_rate_per_tick": 0.001,
      "memory_basis": "x",
      "missed_leakage_rate_per_tick": 0.0009999999999999998,
      "missed_leakage_ratio": 0.9999999999999998,
      "physical_error": 0.003,
      "posterior_leakage_probability_given_flag": 0.9009009009009009,
      "posterior_shortfall_ratio": 0.0,
      "posterior_threshold": 0.75,
      "profile": "nominal_lab_detector_0p90",
      "raw_surviving_d5_d7_improvement": true,
      "raw_volume_reduction_vs_baseline": 4.485683987274657,
      "risk_budget": "mild_decoder_penalty",
      "shot_conditioned_accept": true,
      "target_logical_error": 0.05
    },
    {
      "baseline_distance": 7,
      "baseline_space_time_volume": 826,
      "candidate_distance": 5,
      "candidate_space_time_volume": 386.4,
      "decoder_adjusted_candidate_space_time_volume": 473.34000000000003,
      "decoder_adjusted_surviving_d5_d7_improvement": true,
      "decoder_adjusted_volume_reduction": 1.7450458444247263,
      "decoder_risk_multiplier": 1.225,
      "false_positive_rate_per_tick": 0.001,
      "false_positive_ratio": 1.0,
      "leakage_rate_per_tick": 0.005,
      "max_false_positive_rate_per_tick": 0.001,
      "max_missed_leakage_rate_per_tick": 0.001,
      "memory_basis": "x",
      "missed_leakage_rate_per_tick": 0.0004999999999999999,
      "missed_leakage_ratio": 0.4999999999999999,
      "physical_error": 0.005,
      "posterior_leakage_probability_given_flag": 0.818926296633303,
      "posterior_shortfall_ratio": 0.0,
      "posterior_threshold": 0.75,
      "profile": "nominal_lab_detector_0p90",
      "raw_surviving_d5_d7_improvement": true,
      "raw_volume_reduction_vs_baseline": 2.13768115942029,
      "risk_budget": "mild_decoder_penalty",
      "shot_conditioned_accept": true,
      "target_logical_error": 0.05
    },
    {
      "baseline_distance": 7,
      "baseline_space_time_volume": 826,
      "candidate_distance": 5,
      "candidate_space_time_volume": 377.19999999999993,
      "decoder_adjusted_candidate_space_time_volume": 509.2199999999999,
      "decoder_adjusted_surviving_d5_d7_improvement": true,
      "decoder_adjusted_volume_reduction": 1.6220886846549627,
      "decoder_risk_multiplier": 1.35,
      "false_positive_rate_per_tick": 0.001,
      "false_positive_ratio": 1.0,
      "leakage_rate_per_tick": 0.01,
      "max_false_positive_rate_per_tick": 0.001,
      "max_missed_leakage_rate_per_tick": 0.001,
      "memory_basis": "z",
      "missed_leakage_rate_per_tick": 0.0009999999999999998,
      "missed_leakage_ratio": 0.9999999999999998,
      "physical_error": 0.003,
      "posterior_leakage_probability_given_flag": 0.9009009009009009,
      "posterior_shortfall_ratio": 0.0,
      "posterior_threshold": 0.75,
      "profile": "nominal_lab_detector_0p90",
      "raw_surviving_d5_d7_improvement": true,
      "raw_volume_reduction_vs_baseline": 2.1898197242841997,
      "risk_budget": "mild_decoder_penalty",
      "shot_conditioned_accept": true,
      "target_logical_error": 0.05
    },
    {
      "baseline_distance": 7,
      "baseline_space_time_volume": 826,
      "candidate_distance": 5,
      "candidate_space_time_volume": 386.4,
      "decoder_adjusted_candidate_space_time_volume": 473.34000000000003,
      "decoder_adjusted_surviving_d5_d7_improvement": true,
      "decoder_adjusted_volume_reduction": 1.7450458444247263,
      "decoder_risk_multiplier": 1.225,
      "false_positive_rate_per_tick": 0.001,
      "false_positive_ratio": 1.0,
      "leakage_rate_per_tick": 0.005,
      "max_false_positive_rate_per_tick": 0.001,
      "max_missed_leakage_rate_per_tick": 0.0005,
      "memory_basis": "x",
      "missed_leakage_rate_per_tick": 0.0002500000000000002,
      "missed_leakage_ratio": 0.5000000000000004,
      "physical_error": 0.005,
      "posterior_leakage_probability_given_flag": 0.8268059181897301,
      "posterior_shortfall_ratio": 0.0,
      "posterior_threshold": 0.75,
      "profile": "high_purity_detector_0p95",
      "raw_surviving_d5_d7_improvement": true,
      "raw_volume_reduction_vs_baseline": 2.13768115942029,
      "risk_budget": "mild_decoder_penalty",
      "shot_conditioned_accept": true,
      "target_logical_error": 0.05
    },
    {
      "baseline_distance": 7,
      "baseline_space_time_volume": 826,
      "candidate_distance": 5,
      "candidate_space_time_volume": 386.4,
      "decoder_adjusted_candidate_space_time_volume": 676.1999999999999,
      "decoder_adjusted_surviving_d5_d7_improvement": true,
      "decoder_adjusted_volume_reduction": 1.2215320910973086,
      "decoder_risk_multiplier": 1.75,
      "false_positive_rate_per_tick": 0.001,
      "false_positive_ratio": 1.0,
      "leakage_rate_per_tick": 0.005,
      "max_false_positive_rate_per_tick": 0.001,
      "max_missed_leakage_rate_per_tick": 0.001,
      "memory_basis": "x",
      "missed_leakage_rate_per_tick": 0.0009999999999999998,
      "missed_leakage_ratio": 0.9999999999999998,
      "physical_error": 0.005,
      "posterior_leakage_probability_given_flag": 0.8008008008008007,
      "posterior_shortfall_ratio": 0.0,
      "posterior_threshold": 0.75,
      "profile": "field_detector_0p80",
      "raw_surviving_d5_d7_improvement": true,
      "raw_volume_reduction_vs_baseline": 2.13768115942029,
      "risk_budget": "nominal_decoder_penalty",
      "shot_conditioned_accept": true,
      "target_logical_error": 0.05
    },
    {
      "baseline_distance": 9,
      "baseline_space_time_volume": 1692,
      "candidate_distance": 5,
      "candidate_space_time_volume": 377.19999999999993,
      "decoder_adjusted_candidate_space_time_volume": 660.0999999999999,
      "decoder_adjusted_surviving_d5_d7_improvement": true,
      "decoder_adjusted_volume_reduction": 2.5632479927283747,
      "decoder_risk_multiplier": 1.75,
      "false_positive_rate_per_tick": 0.001,
      "false_positive_ratio": 1.0,
      "leakage_rate_per_tick": 0.01,
      "max_false_positive_rate_per_tick": 0.001,
      "max_missed_leakage_rate_per_tick": 0.001,
      "memory_basis": "x",
      "missed_leakage_rate_per_tick": 0.0009999999999999998,
      "missed_leakage_ratio": 0.9999999999999998,
      "physical_error": 0.003,
      "posterior_leakage_probability_given_flag": 0.9009009009009009,
      "posterior_shortfall_ratio": 0.0,
      "posterior_threshold": 0.75,
      "profile": "nominal_lab_detector_0p90",
      "raw_surviving_d5_d7_improvement": true,
      "raw_volume_reduction_vs_baseline": 4.485683987274657,
      "risk_budget": "nominal_decoder_penalty",
      "shot_conditioned_accept": true,
      "target_logical_error": 0.05
    },
    {
      "baseline_distance": 7,
      "baseline_space_time_volume": 826,
      "candidate_distance": 5,
      "candidate_space_time_volume": 386.4,
      "decoder_adjusted_candidate_space_time_volume": 579.5999999999999,
      "decoder_adjusted_surviving_d5_d7_improvement": true,
      "decoder_adjusted_volume_reduction": 1.4251207729468602,
      "decoder_risk_multiplier": 1.5,
      "false_positive_rate_per_tick": 0.001,
      "false_positive_ratio": 1.0,
      "leakage_rate_per_tick": 0.005,
      "max_false_positive_rate_per_tick": 0.001,
      "max_missed_leakage_rate_per_tick": 0.001,
      "memory_basis": "x",
      "missed_leakage_rate_per_tick": 0.0004999999999999999,
      "missed_leakage_ratio": 0.4999999999999999,
      "physical_error": 0.005,
      "posterior_leakage_probability_given_flag": 0.818926296633303,
      "posterior_shortfall_ratio": 0.0,
      "posterior_threshold": 0.75,
      "profile": "nominal_lab_detector_0p90",
      "raw_surviving_d5_d7_improvement": true,
      "raw_volume_reduction_vs_baseline": 2.13768115942029,
      "risk_budget": "nominal_decoder_penalty",
      "shot_conditioned_accept": true,
      "target_logical_error": 0.05
    },
    {
      "baseline_distance": 7,
      "baseline_space_time_volume": 826,
      "candidate_distance": 5,
      "candidate_space_time_volume": 377.19999999999993,
      "decoder_adjusted_candidate_space_time_volume": 660.0999999999999,
      "decoder_adjusted_surviving_d5_d7_improvement": true,
      "decoder_adjusted_volume_reduction": 1.2513255567338284,
      "decoder_risk_multiplier": 1.75,
      "false_positive_rate_per_tick": 0.001,
      "false_positive_ratio": 1.0,
      "leakage_rate_per_tick": 0.01,
      "max_false_positive_rate_per_tick": 0.001,
      "max_missed_leakage_rate_per_tick": 0.001,
      "memory_basis": "z",
      "missed_leakage_rate_per_tick": 0.0009999999999999998,
      "missed_leakage_ratio": 0.9999999999999998,
      "physical_error": 0.003,
      "posterior_leakage_probability_given_flag": 0.9009009009009009,
      "posterior_shortfall_ratio": 0.0,
      "posterior_threshold": 0.75,
      "profile": "nominal_lab_detector_0p90",
      "raw_surviving_d5_d7_improvement": true,
      "raw_volume_reduction_vs_baseline": 2.1898197242841997,
      "risk_budget": "nominal_decoder_penalty",
      "shot_conditioned_accept": true,
      "target_logical_error": 0.05
    },
    {
      "baseline_distance": 7,
      "baseline_space_time_volume": 826,
      "candidate_distance": 5,
      "candidate_space_time_volume": 386.4,
      "decoder_adjusted_candidate_space_time_volume": 579.6,
      "decoder_adjusted_surviving_d5_d7_improvement": true,
      "decoder_adjusted_volume_reduction": 1.4251207729468598,
      "decoder_risk_multiplier": 1.5000000000000002,
      "false_positive_rate_per_tick": 0.001,
      "false_positive_ratio": 1.0,
      "leakage_rate_per_tick": 0.005,
      "max_false_positive_rate_per_tick": 0.001,
      "max_missed_leakage_rate_per_tick": 0.0005,
      "memory_basis": "x",
      "missed_leakage_rate_per_tick": 0.0002500000000000002,
      "missed_leakage_ratio": 0.5000000000000004,
      "physical_error": 0.005,
      "posterior_leakage_probability_given_flag": 0.8268059181897301,
      "posterior_shortfall_ratio": 0.0,
      "posterior_threshold": 0.75,
      "profile": "high_purity_detector_0p95",
      "raw_surviving_d5_d7_improvement": true,
      "raw_volume_reduction_vs_baseline": 2.13768115942029,
      "risk_budget": "nominal_decoder_penalty",
      "shot_conditioned_accept": true,
      "target_logical_error": 0.05
    },
    {
      "baseline_distance": 9,
      "baseline_space_time_volume": 1692,
      "candidate_distance": 5,
      "candidate_space_time_volume": 377.19999999999993,
      "decoder_adjusted_candidate_space_time_volume": 848.6999999999998,
      "decoder_adjusted_surviving_d5_d7_improvement": true,
      "decoder_adjusted_volume_reduction": 1.9936373276776251,
      "decoder_risk_multiplier": 2.25,
      "false_positive_rate_per_tick": 0.001,
      "false_positive_ratio": 1.0,
      "leakage_rate_per_tick": 0.01,
      "max_false_positive_rate_per_tick": 0.001,
      "max_missed_leakage_rate_per_tick": 0.001,
      "memory_basis": "x",
      "missed_leakage_rate_per_tick": 0.0009999999999999998,
      "missed_leakage_ratio": 0.9999999999999998,
      "physical_error": 0.003,
      "posterior_leakage_probability_given_flag": 0.9009009009009009,
      "posterior_shortfall_ratio": 0.0,
      "posterior_threshold": 0.75,
      "profile": "nominal_lab_detector_0p90",
      "raw_surviving_d5_d7_improvement": true,
      "raw_volume_reduction_vs_baseline": 4.485683987274657,
      "risk_budget": "conservative_decoder_penalty",
      "shot_conditioned_accept": true,
      "target_logical_error": 0.05
    },
    {
      "baseline_distance": 7,
      "baseline_space_time_volume": 826,
      "candidate_distance": 5,
      "candidate_space_time_volume": 386.4,
      "decoder_adjusted_candidate_space_time_volume": 724.5,
      "decoder_adjusted_surviving_d5_d7_improvement": true,
      "decoder_adjusted_volume_reduction": 1.1400966183574879,
      "decoder_risk_multiplier": 1.875,
      "false_positive_rate_per_tick": 0.001,
      "false_positive_ratio": 1.0,
      "leakage_rate_per_tick": 0.005,
      "max_false_positive_rate_per_tick": 0.001,
      "max_missed_leakage_rate_per_tick": 0.001,
      "memory_basis": "x",
      "missed_leakage_rate_per_tick": 0.0004999999999999999,
      "missed_leakage_ratio": 0.4999999999999999,
      "physical_error": 0.005,
      "posterior_leakage_probability_given_flag": 0.818926296633303,
      "posterior_shortfall_ratio": 0.0,
      "posterior_threshold": 0.75,
      "profile": "nominal_lab_detector_0p90",
      "raw_surviving_d5_d7_improvement": true,
      "raw_volume_reduction_vs_baseline": 2.13768115942029,
      "risk_budget": "conservative_decoder_penalty",
      "shot_conditioned_accept": true,
      "target_logical_error": 0.05
    },
    {
      "baseline_distance": 7,
      "baseline_space_time_volume": 826,
      "candidate_distance": 5,
      "candidate_space_time_volume": 386.4,
      "decoder_adjusted_candidate_space_time_volume": 724.5000000000001,
      "decoder_adjusted_surviving_d5_d7_improvement": true,
      "decoder_adjusted_volume_reduction": 1.1400966183574877,
      "decoder_risk_multiplier": 1.8750000000000004,
      "false_positive_rate_per_tick": 0.001,
      "false_positive_ratio": 1.0,
      "leakage_rate_per_tick": 0.005,
      "max_false_positive_rate_per_tick": 0.001,
      "max_missed_leakage_rate_per_tick": 0.0005,
      "memory_basis": "x",
      "missed_leakage_rate_per_tick": 0.0002500000000000002,
      "missed_leakage_ratio": 0.5000000000000004,
      "physical_error": 0.005,
      "posterior_leakage_probability_given_flag": 0.8268059181897301,
      "posterior_shortfall_ratio": 0.0,
      "posterior_threshold": 0.75,
      "profile": "high_purity_detector_0p95",
      "raw_surviving_d5_d7_improvement": true,
      "raw_volume_reduction_vs_baseline": 2.13768115942029,
      "risk_budget": "conservative_decoder_penalty",
      "shot_conditioned_accept": true,
      "target_logical_error": 0.05
    },
    {
      "baseline_distance": 9,
      "baseline_space_time_volume": 1692,
      "candidate_distance": 5,
      "candidate_space_time_volume": 377.19999999999993,
      "decoder_adjusted_candidate_space_time_volume": 942.9999999999998,
      "decoder_adjusted_surviving_d5_d7_improvement": true,
      "decoder_adjusted_volume_reduction": 1.7942735949098625,
      "decoder_risk_multiplier": 2.5,
      "false_positive_rate_per_tick": 0.001,
      "false_positive_ratio": 1.0,
      "leakage_rate_per_tick": 0.01,
      "max_false_positive_rate_per_tick": 0.001,
      "max_missed_leakage_rate_per_tick": 0.001,
      "memory_basis": "x",
      "missed_leakage_rate_per_tick": 0.0009999999999999998,
      "missed_leakage_ratio": 0.9999999999999998,
      "physical_error": 0.003,
      "posterior_leakage_probability_given_flag": 0.9009009009009009,
      "posterior_shortfall_ratio": 0.0,
      "posterior_threshold": 0.75,
      "profile": "nominal_lab_detector_0p90",
      "raw_surviving_d5_d7_improvement": true,
      "raw_volume_reduction_vs_baseline": 4.485683987274657,
      "risk_budget": "strict_decoder_penalty",
      "shot_conditioned_accept": true,
      "target_logical_error": 0.05
    },
    {
      "baseline_distance": 7,
      "baseline_space_time_volume": 826,
      "candidate_distance": 5,
      "candidate_space_time_volume": 386.4,
      "decoder_adjusted_candidate_space_time_volume": 772.8,
      "decoder_adjusted_surviving_d5_d7_improvement": true,
      "decoder_adjusted_volume_reduction": 1.068840579710145,
      "decoder_risk_multiplier": 2.0,
      "false_positive_rate_per_tick": 0.001,
      "false_positive_ratio": 1.0,
      "leakage_rate_per_tick": 0.005,
      "max_false_positive_rate_per_tick": 0.001,
      "max_missed_leakage_rate_per_tick": 0.001,
      "memory_basis": "x",
      "missed_leakage_rate_per_tick": 0.0004999999999999999,
      "missed_leakage_ratio": 0.4999999999999999,
      "physical_error": 0.005,
      "posterior_leakage_probability_given_flag": 0.818926296633303,
      "posterior_shortfall_ratio": 0.0,
      "posterior_threshold": 0.75,
      "profile": "nominal_lab_detector_0p90",
      "raw_surviving_d5_d7_improvement": true,
      "raw_volume_reduction_vs_baseline": 2.13768115942029,
      "risk_budget": "strict_decoder_penalty",
      "shot_conditioned_accept": true,
      "target_logical_error": 0.05
    },
    {
      "baseline_distance": 7,
      "baseline_space_time_volume": 826,
      "candidate_distance": 5,
      "candidate_space_time_volume": 386.4,
      "decoder_adjusted_candidate_space_time_volume": 772.8000000000002,
      "decoder_adjusted_surviving_d5_d7_improvement": true,
      "decoder_adjusted_volume_reduction": 1.0688405797101446,
      "decoder_risk_multiplier": 2.0000000000000004,
      "false_positive_rate_per_tick": 0.001,
      "false_positive_ratio": 1.0,
      "leakage_rate_per_tick": 0.005,
      "max_false_positive_rate_per_tick": 0.001,
      "max_missed_leakage_rate_per_tick": 0.0005,
      "memory_basis": "x",
      "missed_leakage_rate_per_tick": 0.0002500000000000002,
      "missed_leakage_ratio": 0.5000000000000004,
      "physical_error": 0.005,
      "posterior_leakage_probability_given_flag": 0.8268059181897301,
      "posterior_shortfall_ratio": 0.0,
      "posterior_threshold": 0.75,
      "profile": "high_purity_detector_0p95",
      "raw_surviving_d5_d7_improvement": true,
      "raw_volume_reduction_vs_baseline": 2.13768115942029,
      "risk_budget": "strict_decoder_penalty",
      "shot_conditioned_accept": true,
      "target_logical_error": 0.05
    }
  ],
  "benchmark_id": "B2",
  "claim_boundary": {
    "calibrated_device_claimed": false,
    "circuit_level_decoder_claimed": false,
    "distance_3_candidate_used": false,
    "full_physical_leakage_decoder_claimed": false,
    "hardware_result_claimed": false,
    "new_code_claimed": false,
    "posterior_weighted_decoder_risk_model_performed": true,
    "production_decoder_claimed": false,
    "reduced_rounds_used": false,
    "shot_conditioned_erasure_decoder_claimed": false,
    "threshold_claimed": false,
    "what_is_not_supported": "This is not a circuit-level shot-conditioned decoder, production decoder, hardware-calibrated leakage model, threshold result, new code, or hardware QEC result.",
    "what_is_supported": "Posterior-calibrated rows can be re-costed with explicit decoder-risk multipliers; the surviving signal shrinks under conservative and strict risk budgets and still lacks all-profile robustness."
  },
  "last_updated": "2026-06-18",
  "method": "b2_posterior_weighted_decoder_risk_ledger_v0",
  "model_status": "posterior_weighted_risk_ledger_not_circuit_level_decoder",
  "problem_id": 22,
  "risk_budgets": [
    {
      "false_positive_weight": 0.1,
      "minimum_adjusted_reduction": 1.0,
      "missed_leakage_weight": 0.25,
      "name": "mild_decoder_penalty",
      "posterior_shortfall_weight": 1.0
    },
    {
      "false_positive_weight": 0.25,
      "minimum_adjusted_reduction": 1.0,
      "missed_leakage_weight": 0.5,
      "name": "nominal_decoder_penalty",
      "posterior_shortfall_weight": 1.0
    },
    {
      "false_positive_weight": 0.5,
      "minimum_adjusted_reduction": 1.0,
      "missed_leakage_weight": 0.75,
      "name": "conservative_decoder_penalty",
      "posterior_shortfall_weight": 1.0
    },
    {
      "false_positive_weight": 0.5,
      "minimum_adjusted_reduction": 1.0,
      "missed_leakage_weight": 1.0,
      "name": "strict_decoder_penalty",
      "posterior_shortfall_weight": 1.5
    }
  ],
  "source_method": "b2_shot_conditioned_erasure_decoder_boundary_v0",
  "source_result": "results/B2_shot_conditioned_erasure_decoder_boundary_v0.json",
  "source_status": "shot_conditioned_calibrated_leakage_boundary_partial_survival_not_threshold",
  "status": "posterior_weighted_decoder_risk_boundary_not_production_decoder",
  "summary": {
    "by_budget": {
      "conservative_decoder_penalty": {
        "adjusted_surviving_d5_d7_rows": 3,
        "by_profile": {
          "field_detector_0p80": {
            "adjusted_surviving_d5_d7_rows": 0,
            "evaluated_rows": 288
          },
          "high_purity_detector_0p95": {
            "adjusted_surviving_d5_d7_rows": 1,
            "evaluated_rows": 288
          },
          "nominal_lab_detector_0p90": {
            "adjusted_surviving_d5_d7_rows": 2,
            "evaluated_rows": 288
          },
          "strict_high_purity_0p95": {
            "adjusted_surviving_d5_d7_rows": 0,
            "evaluated_rows": 288
          }
        },
        "evaluated_rows": 1152,
        "max_decoder_adjusted_reduction": 1.9936373276776251,
        "mean_decoder_adjusted_reduction": 1.4246101881308668,
        "profiles_with_adjusted_survivors": 2,
        "robust_all_profile_adjusted_survival": false,
        "source_raw_surviving_d5_d7_rows": 6,
        "strict_high_purity_adjusted_survivors": 0,
        "survivor_loss_vs_source": 3
      },
      "mild_decoder_penalty": {
        "adjusted_surviving_d5_d7_rows": 6,
        "by_profile": {
          "field_detector_0p80": {
            "adjusted_surviving_d5_d7_rows": 1,
            "evaluated_rows": 288
          },
          "high_purity_detector_0p95": {
            "adjusted_surviving_d5_d7_rows": 1,
            "evaluated_rows": 288
          },
          "nominal_lab_detector_0p90": {
            "adjusted_surviving_d5_d7_rows": 4,
            "evaluated_rows": 288
          },
          "strict_high_purity_0p95": {
            "adjusted_surviving_d5_d7_rows": 0,
            "evaluated_rows": 288
          }
        },
        "evaluated_rows": 1152,
        "max_decoder_adjusted_reduction": 3.322728879462708,
        "mean_decoder_adjusted_reduction": 1.8842720864485532,
        "profiles_with_adjusted_survivors": 3,
        "robust_all_profile_adjusted_survival": false,
        "source_raw_surviving_d5_d7_rows": 6,
        "strict_high_purity_adjusted_survivors": 0,
        "survivor_loss_vs_source": 0
      },
      "nominal_decoder_penalty": {
        "adjusted_surviving_d5_d7_rows": 5,
        "by_profile": {
          "field_detector_0p80": {
            "adjusted_surviving_d5_d7_rows": 1,
            "evaluated_rows": 288
          },
          "high_purity_detector_0p95": {
            "adjusted_surviving_d5_d7_rows": 1,
            "evaluated_rows": 288
          },
          "nominal_lab_detector_0p90": {
            "adjusted_surviving_d5_d7_rows": 3,
            "evaluated_rows": 288
          },
          "strict_high_purity_0p95": {
            "adjusted_surviving_d5_d7_rows": 0,
            "evaluated_rows": 288
          }
        },
        "evaluated_rows": 1152,
        "max_decoder_adjusted_reduction": 2.5632479927283747,
        "mean_decoder_adjusted_reduction": 1.5772694372906464,
        "profiles_with_adjusted_survivors": 3,
        "robust_all_profile_adjusted_survival": false,
        "source_raw_surviving_d5_d7_rows": 6,
        "strict_high_purity_adjusted_survivors": 0,
        "survivor_loss_vs_source": 1
      },
      "strict_decoder_penalty": {
        "adjusted_surviving_d5_d7_rows": 3,
        "by_profile": {
          "field_detector_0p80": {
            "adjusted_surviving_d5_d7_rows": 0,
            "evaluated_rows": 288
          },
          "high_purity_detector_0p95": {
            "adjusted_surviving_d5_d7_rows": 1,
            "evaluated_rows": 288
          },
          "nominal_lab_detector_0p90": {
            "adjusted_surviving_d5_d7_rows": 2,
            "evaluated_rows": 288
          },
          "strict_high_purity_0p95": {
            "adjusted_surviving_d5_d7_rows": 0,
            "evaluated_rows": 288
          }
        },
        "evaluated_rows": 1152,
        "max_decoder_adjusted_reduction": 1.7942735949098625,
        "mean_decoder_adjusted_reduction": 1.3106515847767175,
        "profiles_with_adjusted_survivors": 2,
        "robust_all_profile_adjusted_survival": false,
        "source_raw_surviving_d5_d7_rows": 6,
        "strict_high_purity_adjusted_survivors": 0,
        "survivor_loss_vs_source": 3
      }
    },
    "conservative_adjusted_surviving_d5_d7_rows": 3,
    "conservative_max_decoder_adjusted_reduction": 1.9936373276776251,
    "evaluated_budget_profile_rows": 4608,
    "mild_adjusted_surviving_d5_d7_rows": 6,
    "nominal_adjusted_surviving_d5_d7_rows": 5,
    "risk_budget_count": 4,
    "robust_all_profile_adjusted_survival": false,
    "source_raw_surviving_d5_d7_rows": 6,
    "strict_adjusted_surviving_d5_d7_rows": 3,
    "strict_high_purity_adjusted_survivors": 0,
    "strict_max_decoder_adjusted_reduction": 1.7942735949098625
  },
  "title": "B2 posterior-weighted decoder-risk ledger",
  "toolchain": "Post-processes T-B2-006 posterior-calibrated profile rows with explicit missed-leakage, false-positive, and posterior-shortfall risk multipliers.",
  "validation_errors": [],
  "version": "0.1"
}
