{
  "process_count": 16,
  "profile_count": 4,
  "profile_rows": [
    {
      "all_replays_within_oracle": false,
      "baseline_selected_vectors": [
        [
          6,
          5,
          4,
          3,
          0,
          1,
          2
        ]
      ],
      "baseline_stable": true,
      "case_count": 33,
      "process_count": 4,
      "process_instance_uuid_count": 4,
      "profile_id": "ascending_f64",
      "replay_count": 264,
      "unique_error_map_payload_hash_count": 33
    },
    {
      "all_replays_within_oracle": false,
      "baseline_selected_vectors": [
        [
          6,
          5,
          4,
          3,
          0,
          1,
          2
        ]
      ],
      "baseline_stable": true,
      "case_count": 33,
      "process_count": 4,
      "process_instance_uuid_count": 4,
      "profile_id": "descending_f64",
      "replay_count": 264,
      "unique_error_map_payload_hash_count": 33
    },
    {
      "all_replays_within_oracle": false,
      "baseline_selected_vectors": [
        [
          6,
          5,
          4,
          3,
          0,
          1,
          2
        ]
      ],
      "baseline_stable": true,
      "case_count": 33,
      "process_count": 4,
      "process_instance_uuid_count": 4,
      "profile_id": "math_fsum",
      "replay_count": 264,
      "unique_error_map_payload_hash_count": 33
    },
    {
      "all_replays_within_oracle": false,
      "baseline_selected_vectors": [
        [
          6,
          5,
          4,
          3,
          0,
          1,
          2
        ]
      ],
      "baseline_stable": true,
      "case_count": 33,
      "process_count": 4,
      "process_instance_uuid_count": 4,
      "profile_id": "exact_binary_fraction",
      "replay_count": 264,
      "unique_error_map_payload_hash_count": 33
    }
  ],
  "profile_summary_payload_hash": "5763fada8be2d0e49374c1a8459dffd6ce89c7052da9505e285747cf9ba4932b",
  "replay_count": 1056
}
